{"nodes": [{"id": "feature_audit_action_plan", "label": "Feature Audit Action Plan", "file_type": "document", "source_file": "FEATURE_AUDIT_ACTION_PLAN.md", "source_location": null, "source_url": null, "captured_at": "2026-05-21", "author": null, "contributor": null}, {"id": "feature_leakage_zero_fill", "label": "Feature Leakage: Zero-Fill Fallback Bug", "file_type": "rationale", "source_file": "FEATURE_AUDIT_ACTION_PLAN.md", "source_location": "line 49-62", "source_url": null, "captured_at": "2026-05-21", "author": null, "contributor": null}, {"id": "feature_leakage_score_in_features", "label": "Feature Leakage: Score in FEATURE_COLUMNS", "file_type": "rationale", "source_file": "FEATURE_AUDIT_ACTION_PLAN.md", "source_location": "line 36-45", "source_url": null, "captured_at": "2026-05-21", "author": null, "contributor": null}], "edges": [{"source": "feature_audit_action_plan", "target": "feature_extractor", "relation": "references", "confidence": "EXTRACTED", "confidence_score": 1.0, "source_file": "FEATURE_AUDIT_ACTION_PLAN.md", "source_location": "line 37, 52, 76, 115, 193", "weight": 1.0}, {"source": "feature_audit_action_plan", "target": "market_data_service", "relation": "references", "confidence": "EXTRACTED", "confidence_score": 1.0, "source_file": "FEATURE_AUDIT_ACTION_PLAN.md", "source_location": "line 24, 92", "weight": 1.0}, {"source": "feature_audit_action_plan", "target": "feature_leakage_zero_fill", "relation": "references", "confidence": "EXTRACTED", "confidence_score": 1.0, "source_file": "FEATURE_AUDIT_ACTION_PLAN.md", "source_location": "P0-3", "weight": 1.0}, {"source": "feature_audit_action_plan", "target": "feature_leakage_score_in_features", "relation": "references", "confidence": "EXTRACTED", "confidence_score": 1.0, "source_file": "FEATURE_AUDIT_ACTION_PLAN.md", "source_location": "P0-2", "weight": 1.0}, {"source": "feature_leakage_zero_fill", "target": "feature_extractor", "relation": "rationale_for", "confidence": "EXTRACTED", "confidence_score": 1.0, "source_file": "FEATURE_AUDIT_ACTION_PLAN.md", "source_location": "P0-3", "weight": 1.0}, {"source": "feature_leakage_score_in_features", "target": "feature_extractor", "relation": "rationale_for", "confidence": "EXTRACTED", "confidence_score": 1.0, "source_file": "FEATURE_AUDIT_ACTION_PLAN.md", "source_location": "P0-2", "weight": 1.0}, {"source": "feature_audit_action_plan", "target": "indicators_provider", "relation": "references", "confidence": "EXTRACTED", "confidence_score": 1.0, "source_file": "FEATURE_AUDIT_ACTION_PLAN.md", "source_location": "P1-5 line 153", "weight": 1.0}, {"source": "feature_audit_action_plan", "target": "indicator_validator", "relation": "references", "confidence": "EXTRACTED", "confidence_score": 1.0, "source_file": "FEATURE_AUDIT_ACTION_PLAN.md", "source_location": "P1-5 line 155", "weight": 1.0}, {"source": "feature_audit_action_plan", "target": "feature_engine", "relation": "references", "confidence": "EXTRACTED", "confidence_score": 1.0, "source_file": "FEATURE_AUDIT_ACTION_PLAN.md", "source_location": "P2-1, P2-2", "weight": 1.0}, {"source": "feature_leakage_zero_fill", "target": "feature_leakage_score_in_features", "relation": "semantically_similar_to", "confidence": "INFERRED", "confidence_score": 0.8, "source_file": "FEATURE_AUDIT_ACTION_PLAN.md", "source_location": null, "weight": 0.8}], "hyperedges": [{"id": "feature_quality_triad", "label": "Feature Quality: FeatureExtractor + FeatureEngine + IndicatorValidator", "nodes": ["feature_extractor", "feature_engine", "indicator_validator"], "relation": "participate_in", "confidence": "INFERRED", "confidence_score": 0.85, "source_file": "FEATURE_AUDIT_ACTION_PLAN.md"}]}