{"nodes": [{"id": "c_users_ricar_default_directory_arquivos_documentos_scalpyn_scalpyn_scalpyn_frontend_public_sw_js", "label": "sw.js", "file_type": "code", "source_file": "C:\\Users\\ricar\\Default Directory\\ARQUIVOS - Documentos\\SCALPYN\\scalpyn\\scalpyn\\frontend\\public\\sw.js", "source_location": "L1"}, {"id": "public_sw_precache_urls", "label": "PRECACHE_URLS", "file_type": "code", "source_file": "C:\\Users\\ricar\\Default Directory\\ARQUIVOS - Documentos\\SCALPYN\\scalpyn\\scalpyn\\frontend\\public\\sw.js", "source_location": "L9"}, {"id": "public_sw_url", "label": "url", "file_type": "code", "source_file": "C:\\Users\\ricar\\Default Directory\\ARQUIVOS - Documentos\\SCALPYN\\scalpyn\\scalpyn\\frontend\\public\\sw.js", "source_location": "L39"}, {"id": "public_sw_clone", "label": "clone", "file_type": "code", "source_file": "C:\\Users\\ricar\\Default Directory\\ARQUIVOS - Documentos\\SCALPYN\\scalpyn\\scalpyn\\frontend\\public\\sw.js", "source_location": "L55"}], "edges": [{"source": "c_users_ricar_default_directory_arquivos_documentos_scalpyn_scalpyn_scalpyn_frontend_public_sw_js", "target": "public_sw_precache_urls", "relation": "contains", "confidence": "EXTRACTED", "source_file": "C:\\Users\\ricar\\Default Directory\\ARQUIVOS - Documentos\\SCALPYN\\scalpyn\\scalpyn\\frontend\\public\\sw.js", "source_location": "L9", "weight": 1.0}, {"source": "c_users_ricar_default_directory_arquivos_documentos_scalpyn_scalpyn_scalpyn_frontend_public_sw_js", "target": "public_sw_url", "relation": "contains", "confidence": "EXTRACTED", "source_file": "C:\\Users\\ricar\\Default Directory\\ARQUIVOS - Documentos\\SCALPYN\\scalpyn\\scalpyn\\frontend\\public\\sw.js", "source_location": "L39", "weight": 1.0}, {"source": "c_users_ricar_default_directory_arquivos_documentos_scalpyn_scalpyn_scalpyn_frontend_public_sw_js", "target": "public_sw_clone", "relation": "contains", "confidence": "EXTRACTED", "source_file": "C:\\Users\\ricar\\Default Directory\\ARQUIVOS - Documentos\\SCALPYN\\scalpyn\\scalpyn\\frontend\\public\\sw.js", "source_location": "L55", "weight": 1.0}], "raw_calls": []}