{
  "nodes": [
    {"id": "collect_market_data_collect_all", "label": "Celery Task: collect_all (ticker/metadata)", "file_type": "code", "source_file": "backend/app/tasks/collect_market_data.py", "source_location": "line 463", "source_url": null, "captured_at": null, "author": null, "contributor": null},
    {"id": "collect_market_data_collect_5m", "label": "Celery Task: collect_5m (OHLCV 5m candles)", "file_type": "code", "source_file": "backend/app/tasks/collect_market_data.py", "source_location": "line 973", "source_url": null, "captured_at": null, "author": null, "contributor": null},
    {"id": "collect_market_data_bulk_upsert_market_metadata", "label": "Bulk UPSERT: market_metadata (anti-deadlock, sorted by symbol)", "file_type": "code", "source_file": "backend/app/tasks/collect_market_data.py", "source_location": "line 21", "source_url": null, "captured_at": null, "author": null, "contributor": null},
    {"id": "collect_market_data_run_async", "label": "_run_async: event loop teardown with asyncpg hard-terminate", "file_type": "code", "source_file": "backend/app/tasks/collect_market_data.py", "source_location": "line 134", "source_url": null, "captured_at": null, "author": null, "contributor": null},
    {"id": "pg_table_market_metadata", "label": "PostgreSQL Table: market_metadata", "file_type": "code", "source_file": "backend/app/tasks/collect_market_data.py", "source_location": "line 50", "source_url": null, "captured_at": null, "author": null, "contributor": null},
    {"id": "pg_table_ohlcv", "label": "PostgreSQL Table: ohlcv (TimescaleDB)", "file_type": "code", "source_file": "backend/app/tasks/collect_market_data.py", "source_location": "line 661", "source_url": null, "captured_at": null, "author": null, "contributor": null},
    {"id": "redis_key_scalpyn_last_collect_all_start", "label": "Redis Key: scalpyn:last_collect_all_start (diagnostics marker)", "file_type": "code", "source_file": "backend/app/tasks/collect_market_data.py", "source_location": "line 469", "source_url": null, "captured_at": null, "author": null, "contributor": null},
    {"id": "redis_key_scalpyn_collect_all_runs", "label": "Redis Key: scalpyn:collect_all_runs (counter)", "file_type": "code", "source_file": "backend/app/tasks/collect_market_data.py", "source_location": "line 470", "source_url": null, "captured_at": null, "author": null, "contributor": null},
    {"id": "collect_market_data_ohlcv_queue_batch", "label": "Persistence Queue: OhlcvBatch message (collect-5m path)", "file_type": "code", "source_file": "backend/app/tasks/collect_market_data.py", "source_location": "line 630", "source_url": null, "captured_at": null, "author": null, "contributor": null},
    {"id": "collect_market_data_market_metadata_queue_upsert", "label": "Persistence Queue: MarketMetadataUpsert message", "file_type": "code", "source_file": "backend/app/tasks/collect_market_data.py", "source_location": "line 642", "source_url": null, "captured_at": null, "author": null, "contributor": null},
    {"id": "collect_market_data_stale_volume_fallback", "label": "Stale volume_24h fallback: per-symbol Gate ticker for symbols missing volume_24h_updated_at > 10min", "file_type": "code", "source_file": "backend/app/tasks/collect_market_data.py", "source_location": "line 877", "source_url": null, "captured_at": null, "author": null, "contributor": null},
    {"id": "collect_market_data_orderbook_savepoint", "label": "Savepoint 2: orderbook metrics UPSERT (spread_pct, orderbook_depth_usdt)", "file_type": "code", "source_file": "backend/app/tasks/collect_market_data.py", "source_location": "line 701", "source_url": null, "captured_at": null, "author": null, "contributor": null},

    {"id": "pipeline_scan_task", "label": "Celery Task: pipeline_scan (L1→L2→L3 every 5m)", "file_type": "code", "source_file": "backend/app/tasks/pipeline_scan.py", "source_location": "line 1", "source_url": null, "captured_at": null, "author": null, "contributor": null},
    {"id": "pipeline_scan_redis_prefix", "label": "Redis Key Prefix: spe:pipeline:{watchlist_id}:signals (L3 prior-signal snapshot)", "file_type": "code", "source_file": "backend/app/tasks/pipeline_scan.py", "source_location": "line 37", "source_url": null, "captured_at": null, "author": null, "contributor": null},
    {"id": "pipeline_scan_live_order_flow_injection", "label": "L3 Live Order Flow Injection: overwrites taker_* / buy_pressure / volume_delta from Redis buffer", "file_type": "code", "source_file": "backend/app/tasks/pipeline_scan.py", "source_location": "line 45", "source_url": null, "captured_at": null, "author": null, "contributor": null},
    {"id": "pipeline_scan_order_flow_window", "label": "L3 Order Flow Window: default 60s (configurable via pipeline config)", "file_type": "code", "source_file": "backend/app/tasks/pipeline_scan.py", "source_location": "line 67", "source_url": null, "captured_at": null, "author": null, "contributor": null},
    {"id": "pipeline_scan_order_flow_max_age", "label": "L3 Order Flow Max Age: default 15s (staleness gate for WS buffer)", "file_type": "code", "source_file": "backend/app/tasks/pipeline_scan.py", "source_location": "line 73", "source_url": null, "captured_at": null, "author": null, "contributor": null},
    {"id": "pipeline_scan_staleness_threshold", "label": "Pipeline Asset Staleness Threshold: default 30 minutes (auto-mark down)", "file_type": "code", "source_file": "backend/app/tasks/pipeline_scan.py", "source_location": "line 41", "source_url": null, "captured_at": null, "author": null, "contributor": null},

    {"id": "order_flow_service_get_order_flow_data", "label": "get_order_flow_data: aggregate taker buy/sell (WS buffer → REST fallback)", "file_type": "code", "source_file": "backend/app/services/order_flow_service.py", "source_location": "line 442", "source_url": null, "captured_at": null, "author": null, "contributor": null},
    {"id": "order_flow_service_read_buffer", "label": "_read_buffer: ZRANGEBYSCORE on trades_buffer:{market_type}:{symbol}", "file_type": "code", "source_file": "backend/app/services/order_flow_service.py", "source_location": "line 312", "source_url": null, "captured_at": null, "author": null, "contributor": null},
    {"id": "redis_key_trades_buffer", "label": "Redis Sorted Set: trades_buffer:{market_type}:{normalized_symbol} (Gate WS spot/futures trades)", "file_type": "code", "source_file": "backend/app/services/order_flow_service.py", "source_location": "line 341", "source_url": null, "captured_at": null, "author": null, "contributor": null},
    {"id": "redis_key_gate_ws_last_handover_ms", "label": "Redis Key: gate_ws:last_handover_ms (WS leader handover tombstone)", "file_type": "code", "source_file": "backend/app/services/order_flow_service.py", "source_location": "line 164", "source_url": null, "captured_at": null, "author": null, "contributor": null},
    {"id": "order_flow_service_safe_taker_ratio", "label": "safe_taker_ratio: buy/(buy+sell), range [0,1], None on zero-activity window", "file_type": "code", "source_file": "backend/app/services/order_flow_service.py", "source_location": "line 108", "source_url": null, "captured_at": null, "author": null, "contributor": null},
    {"id": "order_flow_service_aggregate_buy_sell", "label": "_aggregate_buy_sell: build return dict with audit metadata (n_trades, coverage_pct, partial_window, data_age_seconds)", "file_type": "code", "source_file": "backend/app/services/order_flow_service.py", "source_location": "line 168", "source_url": null, "captured_at": null, "author": null, "contributor": null},
    {"id": "order_flow_service_rest_fallback", "label": "REST Fallback: GET /spot/trades (limit=500, cap detection for partial windows)", "file_type": "code", "source_file": "backend/app/services/order_flow_service.py", "source_location": "line 517", "source_url": null, "captured_at": null, "author": null, "contributor": null},
    {"id": "order_flow_service_handover_taint", "label": "Handover Taint Window: 60s (marks partial_window=True when WS leader recently changed)", "file_type": "code", "source_file": "backend/app/services/order_flow_service.py", "source_location": "line 165", "source_url": null, "captured_at": null, "author": null, "contributor": null},
    {"id": "order_flow_service_redis_fallback_aggregator", "label": "Redis Fallback Aggregator: 5-minute windowed log of symbols that hit REST fallback", "file_type": "code", "source_file": "backend/app/services/order_flow_service.py", "source_location": "line 55", "source_url": null, "captured_at": null, "author": null, "contributor": null},
    {"id": "order_flow_service_taker_window_default", "label": "Order Flow Window Default: 60s (WINDOW_SECONDS), 300s used by compute_indicators tasks", "file_type": "code", "source_file": "backend/app/services/order_flow_service.py", "source_location": "line 52", "source_url": null, "captured_at": null, "author": null, "contributor": null},

    {"id": "market_data_service_class", "label": "MarketDataService: centralized market data (Gate primary, Binance fallback)", "file_type": "code", "source_file": "backend/app/services/market_data_service.py", "source_location": "line 84", "source_url": null, "captured_at": null, "author": null, "contributor": null},
    {"id": "market_data_service_fetch_ohlcv", "label": "fetch_ohlcv: Gate.io primary (≥50 candles), Binance fallback+merge", "file_type": "code", "source_file": "backend/app/services/market_data_service.py", "source_location": "line 405", "source_url": null, "captured_at": null, "author": null, "contributor": null},
    {"id": "market_data_service_min_ohlcv_candles", "label": "MIN_OHLCV_CANDLES = 50 (threshold to trigger Binance merge)", "file_type": "code", "source_file": "backend/app/services/market_data_service.py", "source_location": "line 403", "source_url": null, "captured_at": null, "author": null, "contributor": null},
    {"id": "market_data_service_fetch_all_tickers", "label": "fetch_all_tickers: GET /spot/tickers (bulk, filters ETF/stablecoins)", "file_type": "code", "source_file": "backend/app/services/market_data_service.py", "source_location": "line 544", "source_url": null, "captured_at": null, "author": null, "contributor": null},
    {"id": "market_data_service_fetch_orderbook_metrics", "label": "fetch_orderbook_metrics: spread_pct + orderbook_depth_usdt + bid_ask_imbalance (depth=10)", "file_type": "code", "source_file": "backend/app/services/market_data_service.py", "source_location": "line 564", "source_url": null, "captured_at": null, "author": null, "contributor": null},
    {"id": "market_data_service_normalized", "label": "MarketDataNormalized: symbol, price, volume_base/quote, orderbook_depth, spread_pct, bid_ask_imbalance, orderbook_pressure, taker_ratio, volume_delta", "file_type": "code", "source_file": "backend/app/services/market_data_service.py", "source_location": "line 27", "source_url": null, "captured_at": null, "author": null, "contributor": null},
    {"id": "market_data_service_extract_orderbook_metrics", "label": "_extract_orderbook_metrics: bid_ask_imbalance = (Σbid_qty - Σask_qty)/(Σbid_qty + Σask_qty), range [-1,+1]", "file_type": "code", "source_file": "backend/app/services/market_data_service.py", "source_location": "line 336", "source_url": null, "captured_at": null, "author": null, "contributor": null},
    {"id": "market_data_service_extract_taker_metrics", "label": "_extract_taker_metrics: isBuyerMaker inversion for Binance taker buy/sell computation", "file_type": "code", "source_file": "backend/app/services/market_data_service.py", "source_location": "line 376", "source_url": null, "captured_at": null, "author": null, "contributor": null},
    {"id": "market_data_service_taker_from_binance", "label": "Taker volume from Binance trades (isBuyerMaker field, unavailable on Gate spot)", "file_type": "code", "source_file": "backend/app/services/market_data_service.py", "source_location": "line 789", "source_url": null, "captured_at": null, "author": null, "contributor": null},
    {"id": "gate_spot_candlesticks_url", "label": "Gate.io REST: GET /spot/candlesticks (OHLCV)", "file_type": "code", "source_file": "backend/app/services/market_data_service.py", "source_location": "line 20", "source_url": null, "captured_at": null, "author": null, "contributor": null},
    {"id": "gate_tickers_url", "label": "Gate.io REST: GET /spot/tickers", "file_type": "code", "source_file": "backend/app/services/market_data_service.py", "source_location": "line 21", "source_url": null, "captured_at": null, "author": null, "contributor": null},
    {"id": "gate_orderbook_url", "label": "Gate.io REST: GET /spot/order_book", "file_type": "code", "source_file": "backend/app/services/market_data_service.py", "source_location": "line 22", "source_url": null, "captured_at": null, "author": null, "contributor": null},
    {"id": "gate_funding_url", "label": "Gate.io REST: GET /futures/usdt/funding_rate", "file_type": "code", "source_file": "backend/app/services/market_data_service.py", "source_location": "line 23", "source_url": null, "captured_at": null, "author": null, "contributor": null},
    {"id": "market_data_service_confidence_scores", "label": "Confidence scores: gate=0.7, mixed=varies (seed_service DEFAULT_INDICATORS fallback_config)", "file_type": "code", "source_file": "backend/app/services/market_data_service.py", "source_location": "line 223", "source_url": null, "captured_at": null, "author": null, "contributor": null},

    {"id": "ohlcv_backfill_service_class", "label": "OHLCVBackfillService: chunk-based historical backfill (Gate.io, idempotent)", "file_type": "code", "source_file": "backend/app/services/ohlcv_backfill_service.py", "source_location": "line 19", "source_url": null, "captured_at": null, "author": null, "contributor": null},
    {"id": "ohlcv_backfill_service_backfill_symbol", "label": "backfill_symbol: backwards-in-time chunks, 180 days default, max 3 retries", "file_type": "code", "source_file": "backend/app/services/ohlcv_backfill_service.py", "source_location": "line 43", "source_url": null, "captured_at": null, "author": null, "contributor": null},
    {"id": "ohlcv_backfill_service_validate_candle", "label": "_validate_candle: OHLC relationship check (l<=o<=h, l<=c<=h), positive values, datetime timestamp", "file_type": "code", "source_file": "backend/app/services/ohlcv_backfill_service.py", "source_location": "line 330", "source_url": null, "captured_at": null, "author": null, "contributor": null},
    {"id": "ohlcv_backfill_service_rate_limit", "label": "Backfill rate limit: 0.5s delay, exponential backoff on 429/5xx", "file_type": "code", "source_file": "backend/app/services/ohlcv_backfill_service.py", "source_location": "line 140", "source_url": null, "captured_at": null, "author": null, "contributor": null},

    {"id": "ohlcv_metrics_prometheus", "label": "OHLCV Prometheus Metrics: ohlcv_ingest_received_total, ohlcv_ingest_persisted_total, ohlcv_staleness_seconds", "file_type": "code", "source_file": "backend/app/services/ohlcv_metrics.py", "source_location": "line 1", "source_url": null, "captured_at": null, "author": null, "contributor": null},
    {"id": "ohlcv_metrics_staleness_alert", "label": "Staleness Alert Threshold: ohlcv_staleness_seconds > 1800 triggers ingestion_stale alert", "file_type": "code", "source_file": "backend/app/services/ohlcv_metrics.py", "source_location": "line 16", "source_url": null, "captured_at": null, "author": null, "contributor": null},

    {"id": "ohlcv_repository_class", "label": "OHLCVRepository: bulk_insert (batch 1000), get_earliest/latest_timestamp, count_records, get_data_gaps", "file_type": "code", "source_file": "backend/app/repositories/ohlcv_repository.py", "source_location": "line 13", "source_url": null, "captured_at": null, "author": null, "contributor": null},
    {"id": "ohlcv_repository_conflict_key", "label": "ohlcv unique constraint: ON CONFLICT (time, symbol, exchange, timeframe) DO NOTHING", "file_type": "code", "source_file": "backend/app/repositories/ohlcv_repository.py", "source_location": "line 66", "source_url": null, "captured_at": null, "author": null, "contributor": null},
    {"id": "ohlcv_repository_gap_detection", "label": "get_data_gaps: generate_series LEFT JOIN ohlcv for gap detection by timeframe", "file_type": "code", "source_file": "backend/app/repositories/ohlcv_repository.py", "source_location": "line 150", "source_url": null, "captured_at": null, "author": null, "contributor": null},
    {"id": "ohlcv_repository_timeframe_intervals", "label": "Supported timeframes: 1m, 5m, 15m, 1h, 4h, 1d (seconds mapping)", "file_type": "code", "source_file": "backend/app/repositories/ohlcv_repository.py", "source_location": "line 164", "source_url": null, "captured_at": null, "author": null, "contributor": null},

    {"id": "gate_market_data_parse_gate_spot_candle", "label": "parse_gate_spot_candle: [ts, quote_vol, close, high, low, open, base_vol] → normalized dict", "file_type": "code", "source_file": "backend/app/utils/gate_market_data.py", "source_location": "line 7", "source_url": null, "captured_at": null, "author": null, "contributor": null},
    {"id": "gate_market_data_base_volume_fallback", "label": "Base volume fallback: quote_volume/close when candle[6] absent", "file_type": "code", "source_file": "backend/app/utils/gate_market_data.py", "source_location": "line 22", "source_url": null, "captured_at": null, "author": null, "contributor": null},

    {"id": "spot_scanner_class", "label": "SpotScanner: async spot engine (user-scoped, FeatureEngine + ScoreEngine + GateAdapter)", "file_type": "code", "source_file": "backend/app/engines/spot_scanner.py", "source_location": "line 63", "source_url": null, "captured_at": null, "author": null, "contributor": null},
    {"id": "spot_scanner_get_indicators", "label": "SpotScanner._get_indicators: get_klines 1h limit=200, FeatureEngine.calculate(df)", "file_type": "code", "source_file": "backend/app/engines/spot_scanner.py", "source_location": "line 300", "source_url": null, "captured_at": null, "author": null, "contributor": null},
    {"id": "spot_scanner_feature_config_defaults", "label": "Default feature config: RSI(14), ADX(14), EMA(5,9,21,50,200), ATR(14), MACD(12,26,9), VWAP, Stochastic(14,3,3), OBV, Bollinger(20,2σ), ParabolicSAR(0.02,0.2), ZScore(20), volume_delta", "file_type": "code", "source_file": "backend/app/engines/spot_scanner.py", "source_location": "line 506", "source_url": null, "captured_at": null, "author": null, "contributor": null},
    {"id": "spot_scanner_macro_filter", "label": "SpotScanner macro filter: BTC < EMA200(1d, limit=210) → risk-off, skip buys", "file_type": "code", "source_file": "backend/app/engines/spot_scanner.py", "source_location": "line 404", "source_url": null, "captured_at": null, "author": null, "contributor": null},
    {"id": "spot_scanner_scan_interval", "label": "SpotScanner scan interval: cfg.scanner.scan_interval_seconds (configurable)", "file_type": "code", "source_file": "backend/app/engines/spot_scanner.py", "source_location": "line 181", "source_url": null, "captured_at": null, "author": null, "contributor": null},

    {"id": "futures_scanner_class", "label": "FuturesScanner: 4-gate pipeline (portfolio risk, macro, liquidity, score) + 5-layer scoring", "file_type": "code", "source_file": "backend/app/engines/futures_scanner.py", "source_location": "line 67", "source_url": null, "captured_at": null, "author": null, "contributor": null},
    {"id": "futures_scanner_scan_interval", "label": "FuturesScanner SCAN_INTERVAL = 60s", "file_type": "code", "source_file": "backend/app/engines/futures_scanner.py", "source_location": "line 68", "source_url": null, "captured_at": null, "author": null, "contributor": null},
    {"id": "futures_scanner_l1_liquidity", "label": "FuturesScanner L1: fetch_and_score liquidity (hard_reject threshold)", "file_type": "code", "source_file": "backend/app/engines/futures_scanner.py", "source_location": "line 271", "source_url": null, "captured_at": null, "author": null, "contributor": null},
    {"id": "futures_scanner_l2_structure", "label": "FuturesScanner L2: score_structure (multi-timeframe, l2_timeframes from config)", "file_type": "code", "source_file": "backend/app/engines/futures_scanner.py", "source_location": "line 279", "source_url": null, "captured_at": null, "author": null, "contributor": null},
    {"id": "futures_scanner_l2_primary_tf", "label": "FuturesScanner L2 primary timeframe: 1h (for direction determination)", "file_type": "code", "source_file": "backend/app/engines/futures_scanner.py", "source_location": "line 291", "source_url": null, "captured_at": null, "author": null, "contributor": null},
    {"id": "futures_scanner_l3_momentum", "label": "FuturesScanner L3: score_momentum (primary_df 1h, direction)", "file_type": "code", "source_file": "backend/app/engines/futures_scanner.py", "source_location": "line 317", "source_url": null, "captured_at": null, "author": null, "contributor": null},
    {"id": "futures_scanner_l4_volatility", "label": "FuturesScanner L4: score_volatility (primary_df 1h, ATR-based vol_regime)", "file_type": "code", "source_file": "backend/app/engines/futures_scanner.py", "source_location": "line 321", "source_url": null, "captured_at": null, "author": null, "contributor": null},
    {"id": "futures_scanner_l5_order_flow", "label": "FuturesScanner L5: fetch_order_flow_data + score_order_flow (funding_rate guard)", "file_type": "code", "source_file": "backend/app/engines/futures_scanner.py", "source_location": "line 324", "source_url": null, "captured_at": null, "author": null, "contributor": null},
    {"id": "futures_scanner_funding_guard", "label": "Funding guard: long blocked if funding > funding_extreme, short blocked if funding < -funding_extreme", "file_type": "code", "source_file": "backend/app/engines/futures_scanner.py", "source_location": "line 669", "source_url": null, "captured_at": null, "author": null, "contributor": null},
    {"id": "futures_scanner_gate3_min_score", "label": "Gate 3: min_score_to_trade + min_layer_score for all 5 layers", "file_type": "code", "source_file": "backend/app/engines/futures_scanner.py", "source_location": "line 329", "source_url": null, "captured_at": null, "author": null, "contributor": null},
    {"id": "futures_scanner_klines_per_contract", "label": "FuturesScanner: get_klines per contract per l2_timeframe, limit=200, market=futures", "file_type": "code", "source_file": "backend/app/engines/futures_scanner.py", "source_location": "line 283", "source_url": null, "captured_at": null, "author": null, "contributor": null},

    {"id": "robust_indicators_init", "label": "robust_indicators package (Task #211): deterministic scoring, confidence tracking", "file_type": "code", "source_file": "backend/app/services/robust_indicators/__init__.py", "source_location": "line 1", "source_url": null, "captured_at": null, "author": null, "contributor": null},
    {"id": "robust_indicators_envelope", "label": "IndicatorEnvelope: value + source + timestamp + confidence + staleness_seconds + status (VALID/DEGRADED/NO_DATA/INVALID)", "file_type": "code", "source_file": "backend/app/services/robust_indicators/envelope.py", "source_location": "line 103", "source_url": null, "captured_at": null, "author": null, "contributor": null},
    {"id": "robust_indicators_data_source_enum", "label": "DataSource enum: GATE_TRADES, GATE_CANDLES, GATE_TICKER, GATE_ORDERBOOK, BINANCE_TRADES, BINANCE_CANDLES, BINANCE_TICKER, MERGED, CANDLE_FALLBACK, DERIVED, UNKNOWN", "file_type": "code", "source_file": "backend/app/services/robust_indicators/envelope.py", "source_location": "line 35", "source_url": null, "captured_at": null, "author": null, "contributor": null},
    {"id": "robust_indicators_confidence_map", "label": "CONFIDENCE_MAP: GATE_TRADES=1.0, BINANCE_TRADES=0.95, GATE_ORDERBOOK=0.90, GATE_TICKER=0.85, GATE_CANDLES=0.85, BINANCE_CANDLES=0.80, DERIVED=0.80, CANDLE_FALLBACK=0.40, UNKNOWN=0.30", "file_type": "code", "source_file": "backend/app/services/robust_indicators/envelope.py", "source_location": "line 53", "source_url": null, "captured_at": null, "author": null, "contributor": null},
    {"id": "robust_indicators_staleness_penalty", "label": "STALENESS_PENALTY: 0-60s=1.0x, 60-180s=0.85x, 180-300s=0.50x, >300s=0.10x (applied to base confidence)", "file_type": "code", "source_file": "backend/app/services/robust_indicators/envelope.py", "source_location": "line 70", "source_url": null, "captured_at": null, "author": null, "contributor": null},
    {"id": "robust_indicators_compute", "label": "compute_indicators_robust: FeatureEngine + order_flow_service (300s window) + envelope_indicators", "file_type": "code", "source_file": "backend/app/services/robust_indicators/compute.py", "source_location": "line 173", "source_url": null, "captured_at": null, "author": null, "contributor": null},
    {"id": "robust_indicators_envelope_fn", "label": "envelope_indicators: flat dict → name→IndicatorEnvelope mapping (skips audit metadata keys)", "file_type": "code", "source_file": "backend/app/services/robust_indicators/compute.py", "source_location": "line 119", "source_url": null, "captured_at": null, "author": null, "contributor": null},
    {"id": "robust_indicators_default_source_map", "label": "_DEFAULT_SOURCE_BY_INDICATOR: RSI/ADX/EMA/MACD→GATE_CANDLES, taker_ratio/buy_pressure/volume_delta→GATE_TRADES, spread_pct/orderbook_depth→GATE_ORDERBOOK, volume_24h→GATE_TICKER", "file_type": "code", "source_file": "backend/app/services/robust_indicators/compute.py", "source_location": "line 30", "source_url": null, "captured_at": null, "author": null, "contributor": null},
    {"id": "robust_indicators_no_candle_approximation", "label": "No candle approximation rule: without order-flow data, taker_ratio/volume_delta are dropped (not proxied from candles)", "file_type": "code", "source_file": "backend/app/services/robust_indicators/compute.py", "source_location": "line 260", "source_url": null, "captured_at": null, "author": null, "contributor": null},
    {"id": "robust_indicators_score", "label": "calculate_score_with_confidence: deterministic score = matched_points/total_points * 100 (no confidence weighting)", "file_type": "code", "source_file": "backend/app/services/robust_indicators/score.py", "source_location": "line 201", "source_url": null, "captured_at": null, "author": null, "contributor": null},
    {"id": "robust_indicators_score_result", "label": "ScoreResult: score, score_confidence, can_trade, rejected, components (liquidity/market_structure/momentum/signal), matched_rules, global_confidence", "file_type": "code", "source_file": "backend/app/services/robust_indicators/score.py", "source_location": "line 84", "source_url": null, "captured_at": null, "author": null, "contributor": null},
    {"id": "robust_indicators_can_trade_threshold", "label": "can_trade threshold: score >= 65 AND score_confidence >= 0.60 AND global_confidence >= 0.60", "file_type": "code", "source_file": "backend/app/services/robust_indicators/score.py", "source_location": "line 207", "source_url": null, "captured_at": null, "author": null, "contributor": null},
    {"id": "robust_indicators_validation", "label": "validate_indicator_integrity: 5 CRITICAL rules (bucket exclusivity, critical NO_DATA, flow primary source, derived dependencies, sufficient candles)", "file_type": "code", "source_file": "backend/app/services/robust_indicators/validation.py", "source_location": "line 171", "source_url": null, "captured_at": null, "author": null, "contributor": null},
    {"id": "robust_indicators_critical_indicators", "label": "CRITICAL_INDICATORS: (rsi, adx, macd, ema50) — missing = partial score, not rejection", "file_type": "code", "source_file": "backend/app/services/robust_indicators/validation.py", "source_location": "line 36", "source_url": null, "captured_at": null, "author": null, "contributor": null},
    {"id": "robust_indicators_flow_primary_sources", "label": "FLOW_PRIMARY_SOURCES: GATE_TRADES, BINANCE_TRADES, MERGED (candle fallback rejected as flow source)", "file_type": "code", "source_file": "backend/app/services/robust_indicators/validation.py", "source_location": "line 46", "source_url": null, "captured_at": null, "author": null, "contributor": null},
    {"id": "robust_indicators_bucket_exclusivity", "label": "Bucket exclusivity: taker_buy + taker_sell <= base_volume * 1.05, volume_delta == buy - sell within 5% tolerance", "file_type": "code", "source_file": "backend/app/services/robust_indicators/validation.py", "source_location": "line 122", "source_url": null, "captured_at": null, "author": null, "contributor": null},
    {"id": "robust_indicators_long_warmup_indicators", "label": "LONG_WARMUP_INDICATORS: (ema200, adx, rsi, macd_histogram) — sufficient candles check", "file_type": "code", "source_file": "backend/app/services/robust_indicators/validation.py", "source_location": "line 52", "source_url": null, "captured_at": null, "author": null, "contributor": null},
    {"id": "robust_indicators_derived_deps", "label": "DERIVED_DEPENDENCIES: macd_histogram←(macd, macd_signal_line), ema9_gt_ema50←(ema9, ema50), ema50_gt_ema200←(ema50, ema200), atr_pct←(atr)", "file_type": "code", "source_file": "backend/app/services/robust_indicators/validation.py", "source_location": "line 54", "source_url": null, "captured_at": null, "author": null, "contributor": null},
    {"id": "robust_indicators_asset_score", "label": "compute_asset_score: envelope_indicators + calculate_score_with_confidence → score/score_confidence/global_confidence/matched_rules", "file_type": "code", "source_file": "backend/app/services/robust_indicators/asset_score.py", "source_location": "line 96", "source_url": null, "captured_at": null, "author": null, "contributor": null},
    {"id": "robust_indicators_futures_direction_bias", "label": "robust_futures_direction_bias: [-1,+1] from ema9_gt_ema50, ema50_gt_ema200, macd_histogram sign, rsi zone (>55=long, <45=short)", "file_type": "code", "source_file": "backend/app/services/robust_indicators/asset_score.py", "source_location": "line 23", "source_url": null, "captured_at": null, "author": null, "contributor": null},
    {"id": "robust_indicators_metrics", "label": "Robust Indicators Prometheus: indicator_computation_duration_seconds, indicator_confidence, indicator_staleness_seconds, score_rejection_total, exchange_request_latency_seconds, gate_ws_connected, gate_ws_is_leader, gate_trades_received_total", "file_type": "code", "source_file": "backend/app/services/robust_indicators/metrics.py", "source_location": "line 1", "source_url": null, "captured_at": null, "author": null, "contributor": null},
    {"id": "robust_indicators_snapshot_table", "label": "PostgreSQL Table: indicator_snapshots (UUID, symbol, timestamp, indicators_json JSONB, global_confidence, score, can_trade)", "file_type": "code", "source_file": "backend/app/services/robust_indicators/snapshot.py", "source_location": "line 28", "source_url": null, "captured_at": null, "author": null, "contributor": null},

    {"id": "pipeline_profile_filters_strict_meta", "label": "STRICT_META_FIELDS: volume_24h, market_cap, price, current_price, change_24h, change_24h_pct, price_change_24h, spread_pct (NULL=FAIL, not SKIP)", "file_type": "code", "source_file": "backend/app/utils/pipeline_profile_filters.py", "source_location": "line 20", "source_url": null, "captured_at": null, "author": null, "contributor": null},
    {"id": "pipeline_profile_filters_watchlist_levels", "label": "Pipeline levels: POOL → L1 → L2 → L3 (each requires upstream)", "file_type": "code", "source_file": "backend/app/utils/pipeline_profile_filters.py", "source_location": "line 4", "source_url": null, "captured_at": null, "author": null, "contributor": null},
    {"id": "pipeline_profile_filters_meta_coverage_relax", "label": "STRICT_META_MIN_COVERAGE_RATIO=0.10: relax strict meta filters when < 10% symbols have metadata", "file_type": "code", "source_file": "backend/app/utils/pipeline_profile_filters.py", "source_location": "line 35", "source_url": null, "captured_at": null, "author": null, "contributor": null},

    {"id": "pipeline_rejections_evaluate_rejections", "label": "evaluate_rejections: block_rules + filters + entry_triggers + signals → (approved_assets, rejection_logs)", "file_type": "code", "source_file": "backend/app/services/pipeline_rejections.py", "source_location": "line 704", "source_url": null, "captured_at": null, "author": null, "contributor": null},
    {"id": "pipeline_rejections_build_trace_asset", "label": "build_trace_asset: merge indicators_json (wins) + market_metadata → trace dict (resolves alias spellings)", "file_type": "code", "source_file": "backend/app/services/pipeline_rejections.py", "source_location": "line 105", "source_url": null, "captured_at": null, "author": null, "contributor": null},
    {"id": "pipeline_rejections_block_rule_negative_polarity", "label": "Block rule negative polarity: math PASS = block TRIPPED = asset rejected (outcome=TRIPPED)", "file_type": "code", "source_file": "backend/app/services/pipeline_rejections.py", "source_location": "line 395", "source_url": null, "captured_at": null, "author": null, "contributor": null},
    {"id": "pipeline_rejections_indicator_aliases", "label": "Indicator field aliases: bb_width↔bollinger_width, volume_24h↔volume_24h_usdt, atr_pct↔atr_percent, orderbook_depth_usdt↔orderbook_depth", "file_type": "code", "source_file": "backend/app/services/pipeline_rejections.py", "source_location": "line 93", "source_url": null, "captured_at": null, "author": null, "contributor": null},
    {"id": "pipeline_rejections_recompute_rejection_trace", "label": "recompute_rejection_trace: live recompute from current indicators (Rejected tab, avoids SEM DADOS false-negatives)", "file_type": "code", "source_file": "backend/app/services/pipeline_rejections.py", "source_location": "line 656", "source_url": null, "captured_at": null, "author": null, "contributor": null}
  ],
  "edges": [
    {"source": "collect_market_data_collect_all", "target": "market_data_service_fetch_all_tickers", "relation": "calls", "confidence": "EXTRACTED", "confidence_score": 1.0, "source_file": "backend/app/tasks/collect_market_data.py", "source_location": "line 343", "weight": 1.0},
    {"source": "collect_market_data_collect_all", "target": "pg_table_market_metadata", "relation": "shares_data_with", "confidence": "EXTRACTED", "confidence_score": 1.0, "source_file": "backend/app/tasks/collect_market_data.py", "source_location": "line 50", "weight": 1.0},
    {"source": "collect_market_data_collect_all", "target": "collect_market_data_bulk_upsert_market_metadata", "relation": "calls", "confidence": "EXTRACTED", "confidence_score": 1.0, "source_file": "backend/app/tasks/collect_market_data.py", "source_location": "line 404", "weight": 1.0},
    {"source": "collect_market_data_collect_all", "target": "redis_key_scalpyn_last_collect_all_start", "relation": "shares_data_with", "confidence": "EXTRACTED", "confidence_score": 1.0, "source_file": "backend/app/tasks/collect_market_data.py", "source_location": "line 469", "weight": 1.0},
    {"source": "collect_market_data_collect_all", "target": "redis_key_scalpyn_collect_all_runs", "relation": "shares_data_with", "confidence": "EXTRACTED", "confidence_score": 1.0, "source_file": "backend/app/tasks/collect_market_data.py", "source_location": "line 470", "weight": 1.0},
    {"source": "collect_market_data_collect_5m", "target": "market_data_service_fetch_ohlcv", "relation": "calls", "confidence": "EXTRACTED", "confidence_score": 1.0, "source_file": "backend/app/tasks/collect_market_data.py", "source_location": "line 587", "weight": 1.0},
    {"source": "collect_market_data_collect_5m", "target": "market_data_service_fetch_orderbook_metrics", "relation": "calls", "confidence": "EXTRACTED", "confidence_score": 1.0, "source_file": "backend/app/tasks/collect_market_data.py", "source_location": "line 708", "weight": 1.0},
    {"source": "collect_market_data_collect_5m", "target": "pg_table_ohlcv", "relation": "shares_data_with", "confidence": "EXTRACTED", "confidence_score": 1.0, "source_file": "backend/app/tasks/collect_market_data.py", "source_location": "line 661", "weight": 1.0},
    {"source": "collect_market_data_collect_5m", "target": "pg_table_market_metadata", "relation": "shares_data_with", "confidence": "EXTRACTED", "confidence_score": 1.0, "source_file": "backend/app/tasks/collect_market_data.py", "source_location": "line 727", "weight": 1.0},
    {"source": "collect_market_data_collect_5m", "target": "collect_market_data_ohlcv_queue_batch", "relation": "shares_data_with", "confidence": "EXTRACTED", "confidence_score": 1.0, "source_file": "backend/app/tasks/collect_market_data.py", "source_location": "line 630", "weight": 1.0},
    {"source": "collect_market_data_collect_5m", "target": "collect_market_data_stale_volume_fallback", "relation": "calls", "confidence": "EXTRACTED", "confidence_score": 1.0, "source_file": "backend/app/tasks/collect_market_data.py", "source_location": "line 877", "weight": 1.0},
    {"source": "collect_market_data_collect_5m", "target": "collect_market_data_orderbook_savepoint", "relation": "calls", "confidence": "EXTRACTED", "confidence_score": 1.0, "source_file": "backend/app/tasks/collect_market_data.py", "source_location": "line 701", "weight": 1.0},
    {"source": "collect_market_data_stale_volume_fallback", "target": "pg_table_market_metadata", "relation": "references", "confidence": "EXTRACTED", "confidence_score": 1.0, "source_file": "backend/app/tasks/collect_market_data.py", "source_location": "line 882", "weight": 1.0},
    {"source": "collect_market_data_stale_volume_fallback", "target": "gate_tickers_url", "relation": "references", "confidence": "INFERRED", "confidence_score": 0.95, "source_file": "backend/app/tasks/collect_market_data.py", "source_location": "line 896", "weight": 0.9},
    {"source": "collect_market_data_bulk_upsert_market_metadata", "target": "pg_table_market_metadata", "relation": "shares_data_with", "confidence": "EXTRACTED", "confidence_score": 1.0, "source_file": "backend/app/tasks/collect_market_data.py", "source_location": "line 50", "weight": 1.0},

    {"source": "pipeline_scan_task", "target": "pipeline_scan_live_order_flow_injection", "relation": "implements", "confidence": "EXTRACTED", "confidence_score": 1.0, "source_file": "backend/app/tasks/pipeline_scan.py", "source_location": "line 45", "weight": 1.0},
    {"source": "pipeline_scan_task", "target": "pipeline_scan_redis_prefix", "relation": "shares_data_with", "confidence": "EXTRACTED", "confidence_score": 1.0, "source_file": "backend/app/tasks/pipeline_scan.py", "source_location": "line 37", "weight": 1.0},
    {"source": "pipeline_scan_live_order_flow_injection", "target": "order_flow_service_get_order_flow_data", "relation": "calls", "confidence": "EXTRACTED", "confidence_score": 1.0, "source_file": "backend/app/tasks/pipeline_scan.py", "source_location": "line 56", "weight": 1.0},
    {"source": "pipeline_scan_live_order_flow_injection", "target": "pipeline_scan_order_flow_window", "relation": "references", "confidence": "EXTRACTED", "confidence_score": 1.0, "source_file": "backend/app/tasks/pipeline_scan.py", "source_location": "line 66", "weight": 1.0},
    {"source": "pipeline_scan_live_order_flow_injection", "target": "pipeline_scan_order_flow_max_age", "relation": "references", "confidence": "EXTRACTED", "confidence_score": 1.0, "source_file": "backend/app/tasks/pipeline_scan.py", "source_location": "line 73", "weight": 1.0},
    {"source": "pipeline_scan_task", "target": "pipeline_rejections_evaluate_rejections", "relation": "calls", "confidence": "EXTRACTED", "confidence_score": 1.0, "source_file": "backend/app/tasks/pipeline_scan.py", "source_location": "line 24", "weight": 1.0},
    {"source": "pipeline_scan_task", "target": "pipeline_profile_filters_strict_meta", "relation": "references", "confidence": "EXTRACTED", "confidence_score": 1.0, "source_file": "backend/app/tasks/pipeline_scan.py", "source_location": "line 26", "weight": 1.0},

    {"source": "order_flow_service_get_order_flow_data", "target": "order_flow_service_read_buffer", "relation": "calls", "confidence": "EXTRACTED", "confidence_score": 1.0, "source_file": "backend/app/services/order_flow_service.py", "source_location": "line 485", "weight": 1.0},
    {"source": "order_flow_service_get_order_flow_data", "target": "order_flow_service_rest_fallback", "relation": "calls", "confidence": "EXTRACTED", "confidence_score": 1.0, "source_file": "backend/app/services/order_flow_service.py", "source_location": "line 517", "weight": 1.0},
    {"source": "order_flow_service_read_buffer", "target": "redis_key_trades_buffer", "relation": "shares_data_with", "confidence": "EXTRACTED", "confidence_score": 1.0, "source_file": "backend/app/services/order_flow_service.py", "source_location": "line 341", "weight": 1.0},
    {"source": "order_flow_service_read_buffer", "target": "redis_key_gate_ws_last_handover_ms", "relation": "shares_data_with", "confidence": "EXTRACTED", "confidence_score": 1.0, "source_file": "backend/app/services/order_flow_service.py", "source_location": "line 358", "weight": 1.0},
    {"source": "order_flow_service_read_buffer", "target": "order_flow_service_handover_taint", "relation": "references", "confidence": "EXTRACTED", "confidence_score": 1.0, "source_file": "backend/app/services/order_flow_service.py", "source_location": "line 424", "weight": 1.0},
    {"source": "order_flow_service_get_order_flow_data", "target": "order_flow_service_safe_taker_ratio", "relation": "calls", "confidence": "EXTRACTED", "confidence_score": 1.0, "source_file": "backend/app/services/order_flow_service.py", "source_location": "line 255", "weight": 1.0},
    {"source": "order_flow_service_get_order_flow_data", "target": "order_flow_service_aggregate_buy_sell", "relation": "calls", "confidence": "EXTRACTED", "confidence_score": 1.0, "source_file": "backend/app/services/order_flow_service.py", "source_location": "line 428", "weight": 1.0},
    {"source": "order_flow_service_rest_fallback", "target": "order_flow_service_redis_fallback_aggregator", "relation": "calls", "confidence": "EXTRACTED", "confidence_score": 1.0, "source_file": "backend/app/services/order_flow_service.py", "source_location": "line 501", "weight": 1.0},

    {"source": "market_data_service_fetch_ohlcv", "target": "gate_spot_candlesticks_url", "relation": "calls", "confidence": "EXTRACTED", "confidence_score": 1.0, "source_file": "backend/app/services/market_data_service.py", "source_location": "line 436", "weight": 1.0},
    {"source": "market_data_service_fetch_ohlcv", "target": "gate_market_data_parse_gate_spot_candle", "relation": "calls", "confidence": "EXTRACTED", "confidence_score": 1.0, "source_file": "backend/app/services/market_data_service.py", "source_location": "line 451", "weight": 1.0},
    {"source": "market_data_service_fetch_ohlcv", "target": "market_data_service_min_ohlcv_candles", "relation": "references", "confidence": "EXTRACTED", "confidence_score": 1.0, "source_file": "backend/app/services/market_data_service.py", "source_location": "line 456", "weight": 1.0},
    {"source": "market_data_service_fetch_all_tickers", "target": "gate_tickers_url", "relation": "calls", "confidence": "EXTRACTED", "confidence_score": 1.0, "source_file": "backend/app/services/market_data_service.py", "source_location": "line 548", "weight": 1.0},
    {"source": "market_data_service_fetch_orderbook_metrics", "target": "gate_orderbook_url", "relation": "calls", "confidence": "EXTRACTED", "confidence_score": 1.0, "source_file": "backend/app/services/market_data_service.py", "source_location": "line 250", "weight": 1.0},
    {"source": "market_data_service_fetch_orderbook_metrics", "target": "market_data_service_extract_orderbook_metrics", "relation": "calls", "confidence": "EXTRACTED", "confidence_score": 1.0, "source_file": "backend/app/services/market_data_service.py", "source_location": "line 336", "weight": 1.0},
    {"source": "market_data_service_class", "target": "market_data_service_taker_from_binance", "relation": "implements", "confidence": "EXTRACTED", "confidence_score": 1.0, "source_file": "backend/app/services/market_data_service.py", "source_location": "line 789", "weight": 1.0},
    {"source": "market_data_service_extract_taker_metrics", "target": "market_data_service_taker_from_binance", "relation": "implements", "confidence": "EXTRACTED", "confidence_score": 1.0, "source_file": "backend/app/services/market_data_service.py", "source_location": "line 376", "weight": 1.0},
    {"source": "market_data_service_class", "target": "market_data_service_confidence_scores", "relation": "references", "confidence": "EXTRACTED", "confidence_score": 1.0, "source_file": "backend/app/services/market_data_service.py", "source_location": "line 223", "weight": 1.0},

    {"source": "ohlcv_backfill_service_class", "target": "gate_spot_candlesticks_url", "relation": "calls", "confidence": "EXTRACTED", "confidence_score": 1.0, "source_file": "backend/app/services/ohlcv_backfill_service.py", "source_location": "line 16", "weight": 1.0},
    {"source": "ohlcv_backfill_service_class", "target": "gate_market_data_parse_gate_spot_candle", "relation": "calls", "confidence": "EXTRACTED", "confidence_score": 1.0, "source_file": "backend/app/services/ohlcv_backfill_service.py", "source_location": "line 110", "weight": 1.0},
    {"source": "ohlcv_backfill_service_class", "target": "ohlcv_repository_class", "relation": "calls", "confidence": "EXTRACTED", "confidence_score": 1.0, "source_file": "backend/app/services/ohlcv_backfill_service.py", "source_location": "line 37", "weight": 1.0},
    {"source": "ohlcv_backfill_service_backfill_symbol", "target": "ohlcv_backfill_service_validate_candle", "relation": "calls", "confidence": "EXTRACTED", "confidence_score": 1.0, "source_file": "backend/app/services/ohlcv_backfill_service.py", "source_location": "line 111", "weight": 1.0},
    {"source": "ohlcv_backfill_service_backfill_symbol", "target": "ohlcv_backfill_service_rate_limit", "relation": "references", "confidence": "EXTRACTED", "confidence_score": 1.0, "source_file": "backend/app/services/ohlcv_backfill_service.py", "source_location": "line 140", "weight": 1.0},
    {"source": "ohlcv_backfill_service_class", "target": "pg_table_ohlcv", "relation": "shares_data_with", "confidence": "EXTRACTED", "confidence_score": 1.0, "source_file": "backend/app/services/ohlcv_backfill_service.py", "source_location": "line 63", "weight": 1.0},

    {"source": "ohlcv_repository_class", "target": "pg_table_ohlcv", "relation": "shares_data_with", "confidence": "EXTRACTED", "confidence_score": 1.0, "source_file": "backend/app/repositories/ohlcv_repository.py", "source_location": "line 64", "weight": 1.0},
    {"source": "ohlcv_repository_class", "target": "ohlcv_repository_conflict_key", "relation": "implements", "confidence": "EXTRACTED", "confidence_score": 1.0, "source_file": "backend/app/repositories/ohlcv_repository.py", "source_location": "line 66", "weight": 1.0},
    {"source": "ohlcv_repository_class", "target": "ohlcv_repository_gap_detection", "relation": "implements", "confidence": "EXTRACTED", "confidence_score": 1.0, "source_file": "backend/app/repositories/ohlcv_repository.py", "source_location": "line 150", "weight": 1.0},
    {"source": "ohlcv_repository_gap_detection", "target": "ohlcv_repository_timeframe_intervals", "relation": "references", "confidence": "EXTRACTED", "confidence_score": 1.0, "source_file": "backend/app/repositories/ohlcv_repository.py", "source_location": "line 164", "weight": 1.0},

    {"source": "spot_scanner_class", "target": "spot_scanner_get_indicators", "relation": "calls", "confidence": "EXTRACTED", "confidence_score": 1.0, "source_file": "backend/app/engines/spot_scanner.py", "source_location": "line 259", "weight": 1.0},
    {"source": "spot_scanner_get_indicators", "target": "spot_scanner_feature_config_defaults", "relation": "references", "confidence": "EXTRACTED", "confidence_score": 1.0, "source_file": "backend/app/engines/spot_scanner.py", "source_location": "line 301", "weight": 1.0},
    {"source": "spot_scanner_class", "target": "spot_scanner_macro_filter", "relation": "calls", "confidence": "EXTRACTED", "confidence_score": 1.0, "source_file": "backend/app/engines/spot_scanner.py", "source_location": "line 203", "weight": 1.0},
    {"source": "spot_scanner_class", "target": "gate_tickers_url", "relation": "references", "confidence": "INFERRED", "confidence_score": 0.95, "source_file": "backend/app/engines/spot_scanner.py", "source_location": "line 185", "weight": 0.9},

    {"source": "futures_scanner_class", "target": "futures_scanner_l1_liquidity", "relation": "calls", "confidence": "EXTRACTED", "confidence_score": 1.0, "source_file": "backend/app/engines/futures_scanner.py", "source_location": "line 271", "weight": 1.0},
    {"source": "futures_scanner_class", "target": "futures_scanner_l2_structure", "relation": "calls", "confidence": "EXTRACTED", "confidence_score": 1.0, "source_file": "backend/app/engines/futures_scanner.py", "source_location": "line 315", "weight": 1.0},
    {"source": "futures_scanner_class", "target": "futures_scanner_l3_momentum", "relation": "calls", "confidence": "EXTRACTED", "confidence_score": 1.0, "source_file": "backend/app/engines/futures_scanner.py", "source_location": "line 317", "weight": 1.0},
    {"source": "futures_scanner_class", "target": "futures_scanner_l4_volatility", "relation": "calls", "confidence": "EXTRACTED", "confidence_score": 1.0, "source_file": "backend/app/engines/futures_scanner.py", "source_location": "line 321", "weight": 1.0},
    {"source": "futures_scanner_class", "target": "futures_scanner_l5_order_flow", "relation": "calls", "confidence": "EXTRACTED", "confidence_score": 1.0, "source_file": "backend/app/engines/futures_scanner.py", "source_location": "line 324", "weight": 1.0},
    {"source": "futures_scanner_l5_order_flow", "target": "futures_scanner_funding_guard", "relation": "references", "confidence": "EXTRACTED", "confidence_score": 1.0, "source_file": "backend/app/engines/futures_scanner.py", "source_location": "line 669", "weight": 1.0},
    {"source": "futures_scanner_class", "target": "futures_scanner_gate3_min_score", "relation": "implements", "confidence": "EXTRACTED", "confidence_score": 1.0, "source_file": "backend/app/engines/futures_scanner.py", "source_location": "line 329", "weight": 1.0},
    {"source": "futures_scanner_class", "target": "futures_scanner_klines_per_contract", "relation": "calls", "confidence": "EXTRACTED", "confidence_score": 1.0, "source_file": "backend/app/engines/futures_scanner.py", "source_location": "line 283", "weight": 1.0},
    {"source": "futures_scanner_l2_structure", "target": "futures_scanner_l2_primary_tf", "relation": "references", "confidence": "EXTRACTED", "confidence_score": 1.0, "source_file": "backend/app/engines/futures_scanner.py", "source_location": "line 291", "weight": 1.0},
    {"source": "futures_scanner_l5_order_flow", "target": "gate_funding_url", "relation": "references", "confidence": "INFERRED", "confidence_score": 0.85, "source_file": "backend/app/engines/futures_scanner.py", "source_location": "line 324", "weight": 0.85},

    {"source": "robust_indicators_compute", "target": "order_flow_service_get_order_flow_data", "relation": "calls", "confidence": "EXTRACTED", "confidence_score": 1.0, "source_file": "backend/app/services/robust_indicators/compute.py", "source_location": "line 225", "weight": 1.0},
    {"source": "robust_indicators_compute", "target": "robust_indicators_envelope_fn", "relation": "calls", "confidence": "EXTRACTED", "confidence_score": 1.0, "source_file": "backend/app/services/robust_indicators/compute.py", "source_location": "line 267", "weight": 1.0},
    {"source": "robust_indicators_compute", "target": "robust_indicators_no_candle_approximation", "relation": "implements", "confidence": "EXTRACTED", "confidence_score": 1.0, "source_file": "backend/app/services/robust_indicators/compute.py", "source_location": "line 260", "weight": 1.0},
    {"source": "robust_indicators_envelope_fn", "target": "robust_indicators_default_source_map", "relation": "references", "confidence": "EXTRACTED", "confidence_score": 1.0, "source_file": "backend/app/services/robust_indicators/compute.py", "source_location": "line 162", "weight": 1.0},
    {"source": "robust_indicators_envelope_fn", "target": "robust_indicators_envelope", "relation": "calls", "confidence": "EXTRACTED", "confidence_score": 1.0, "source_file": "backend/app/services/robust_indicators/compute.py", "source_location": "line 165", "weight": 1.0},
    {"source": "robust_indicators_envelope", "target": "robust_indicators_confidence_map", "relation": "references", "confidence": "EXTRACTED", "confidence_score": 1.0, "source_file": "backend/app/services/robust_indicators/envelope.py", "source_location": "line 172", "weight": 1.0},
    {"source": "robust_indicators_envelope", "target": "robust_indicators_staleness_penalty", "relation": "references", "confidence": "EXTRACTED", "confidence_score": 1.0, "source_file": "backend/app/services/robust_indicators/envelope.py", "source_location": "line 181", "weight": 1.0},
    {"source": "robust_indicators_score", "target": "robust_indicators_can_trade_threshold", "relation": "implements", "confidence": "EXTRACTED", "confidence_score": 1.0, "source_file": "backend/app/services/robust_indicators/score.py", "source_location": "line 307", "weight": 1.0},
    {"source": "robust_indicators_score", "target": "robust_indicators_critical_indicators", "relation": "references", "confidence": "EXTRACTED", "confidence_score": 1.0, "source_file": "backend/app/services/robust_indicators/score.py", "source_location": "line 55", "weight": 1.0},
    {"source": "robust_indicators_validation", "target": "robust_indicators_flow_primary_sources", "relation": "references", "confidence": "EXTRACTED", "confidence_score": 1.0, "source_file": "backend/app/services/robust_indicators/validation.py", "source_location": "line 184", "weight": 1.0},
    {"source": "robust_indicators_validation", "target": "robust_indicators_bucket_exclusivity", "relation": "calls", "confidence": "EXTRACTED", "confidence_score": 1.0, "source_file": "backend/app/services/robust_indicators/validation.py", "source_location": "line 189", "weight": 1.0},
    {"source": "robust_indicators_validation", "target": "robust_indicators_long_warmup_indicators", "relation": "references", "confidence": "EXTRACTED", "confidence_score": 1.0, "source_file": "backend/app/services/robust_indicators/validation.py", "source_location": "line 280", "weight": 1.0},
    {"source": "robust_indicators_validation", "target": "robust_indicators_derived_deps", "relation": "references", "confidence": "EXTRACTED", "confidence_score": 1.0, "source_file": "backend/app/services/robust_indicators/validation.py", "source_location": "line 253", "weight": 1.0},
    {"source": "robust_indicators_asset_score", "target": "robust_indicators_envelope_fn", "relation": "calls", "confidence": "EXTRACTED", "confidence_score": 1.0, "source_file": "backend/app/services/robust_indicators/asset_score.py", "source_location": "line 129", "weight": 1.0},
    {"source": "robust_indicators_asset_score", "target": "robust_indicators_score", "relation": "calls", "confidence": "EXTRACTED", "confidence_score": 1.0, "source_file": "backend/app/services/robust_indicators/asset_score.py", "source_location": "line 135", "weight": 1.0},
    {"source": "robust_indicators_asset_score", "target": "robust_indicators_futures_direction_bias", "relation": "calls", "confidence": "EXTRACTED", "confidence_score": 1.0, "source_file": "backend/app/services/robust_indicators/asset_score.py", "source_location": "line 153", "weight": 1.0},
    {"source": "robust_indicators_snapshot_table", "target": "robust_indicators_score_result", "relation": "shares_data_with", "confidence": "EXTRACTED", "confidence_score": 1.0, "source_file": "backend/app/services/robust_indicators/snapshot.py", "source_location": "line 99", "weight": 1.0},
    {"source": "robust_indicators_metrics", "target": "redis_key_trades_buffer", "relation": "conceptually_related_to", "confidence": "INFERRED", "confidence_score": 0.85, "source_file": "backend/app/services/robust_indicators/metrics.py", "source_location": "line 124", "weight": 0.85},

    {"source": "pipeline_profile_filters_strict_meta", "target": "pg_table_market_metadata", "relation": "references", "confidence": "INFERRED", "confidence_score": 0.95, "source_file": "backend/app/utils/pipeline_profile_filters.py", "source_location": "line 20", "weight": 0.9},
    {"source": "pipeline_profile_filters_meta_coverage_relax", "target": "pipeline_profile_filters_strict_meta", "relation": "references", "confidence": "EXTRACTED", "confidence_score": 1.0, "source_file": "backend/app/utils/pipeline_profile_filters.py", "source_location": "line 141", "weight": 1.0},
    {"source": "pipeline_scan_task", "target": "pipeline_profile_filters_watchlist_levels", "relation": "references", "confidence": "EXTRACTED", "confidence_score": 1.0, "source_file": "backend/app/tasks/pipeline_scan.py", "source_location": "line 163", "weight": 1.0},

    {"source": "pipeline_rejections_build_trace_asset", "target": "pipeline_rejections_indicator_aliases", "relation": "implements", "confidence": "EXTRACTED", "confidence_score": 1.0, "source_file": "backend/app/services/pipeline_rejections.py", "source_location": "line 154", "weight": 1.0},
    {"source": "pipeline_rejections_evaluate_rejections", "target": "pipeline_rejections_build_trace_asset", "relation": "calls", "confidence": "INFERRED", "confidence_score": 0.95, "source_file": "backend/app/services/pipeline_rejections.py", "source_location": "line 689", "weight": 0.95},
    {"source": "pipeline_rejections_evaluate_rejections", "target": "pipeline_rejections_block_rule_negative_polarity", "relation": "implements", "confidence": "EXTRACTED", "confidence_score": 1.0, "source_file": "backend/app/services/pipeline_rejections.py", "source_location": "line 395", "weight": 1.0},
    {"source": "pipeline_rejections_recompute_rejection_trace", "target": "pipeline_rejections_build_trace_asset", "relation": "calls", "confidence": "EXTRACTED", "confidence_score": 1.0, "source_file": "backend/app/services/pipeline_rejections.py", "source_location": "line 689", "weight": 1.0},

    {"source": "order_flow_service_safe_taker_ratio", "target": "robust_indicators_flow_primary_sources", "relation": "conceptually_related_to", "confidence": "INFERRED", "confidence_score": 0.85, "source_file": "backend/app/services/order_flow_service.py", "source_location": "line 104", "weight": 0.85},
    {"source": "robust_indicators_bucket_exclusivity", "target": "order_flow_service_safe_taker_ratio", "relation": "conceptually_related_to", "confidence": "INFERRED", "confidence_score": 0.85, "source_file": "backend/app/services/robust_indicators/validation.py", "source_location": "line 122", "weight": 0.85},

    {"source": "collect_market_data_collect_5m", "target": "ohlcv_metrics_prometheus", "relation": "references", "confidence": "INFERRED", "confidence_score": 0.75, "source_file": "backend/app/tasks/collect_market_data.py", "source_location": null, "weight": 0.75},
    {"source": "ohlcv_metrics_staleness_alert", "target": "ohlcv_metrics_prometheus", "relation": "implements", "confidence": "EXTRACTED", "confidence_score": 1.0, "source_file": "backend/app/services/ohlcv_metrics.py", "source_location": "line 16", "weight": 1.0},

    {"source": "spot_scanner_get_indicators", "target": "market_data_service_fetch_ohlcv", "relation": "conceptually_related_to", "confidence": "INFERRED", "confidence_score": 0.75, "source_file": "backend/app/engines/spot_scanner.py", "source_location": "line 301", "weight": 0.75},
    {"source": "futures_scanner_klines_per_contract", "target": "market_data_service_fetch_ohlcv", "relation": "conceptually_related_to", "confidence": "INFERRED", "confidence_score": 0.75, "source_file": "backend/app/engines/futures_scanner.py", "source_location": "line 283", "weight": 0.75},

    {"source": "market_data_service_fetch_ohlcv", "target": "market_data_service_min_ohlcv_candles", "relation": "references", "confidence": "EXTRACTED", "confidence_score": 1.0, "source_file": "backend/app/services/market_data_service.py", "source_location": "line 456", "weight": 1.0},
    {"source": "robust_indicators_long_warmup_indicators", "target": "market_data_service_min_ohlcv_candles", "relation": "conceptually_related_to", "confidence": "INFERRED", "confidence_score": 0.75, "source_file": "backend/app/services/robust_indicators/validation.py", "source_location": "line 52", "weight": 0.75},

    {"source": "gate_market_data_base_volume_fallback", "target": "gate_market_data_parse_gate_spot_candle", "relation": "implements", "confidence": "EXTRACTED", "confidence_score": 1.0, "source_file": "backend/app/utils/gate_market_data.py", "source_location": "line 22", "weight": 1.0},
    {"source": "market_data_service_fetch_all_tickers", "target": "collect_market_data_collect_all", "relation": "conceptually_related_to", "confidence": "INFERRED", "confidence_score": 0.85, "source_file": "backend/app/services/market_data_service.py", "source_location": "line 344", "weight": 0.85},

    {"source": "robust_indicators_compute", "target": "order_flow_service_taker_window_default", "relation": "references", "confidence": "EXTRACTED", "confidence_score": 1.0, "source_file": "backend/app/services/robust_indicators/compute.py", "source_location": "line 225", "weight": 1.0},
    {"source": "pipeline_scan_order_flow_window", "target": "order_flow_service_taker_window_default", "relation": "conceptually_related_to", "confidence": "INFERRED", "confidence_score": 0.85, "source_file": "backend/app/tasks/pipeline_scan.py", "source_location": "line 67", "weight": 0.85}
  ],
  "hyperedges": [
    {
      "id": "ohlcv_ingestion_pipeline_5m",
      "label": "5m OHLCV Ingestion Pipeline (collect_5m → ohlcv table → compute chain)",
      "nodes": ["collect_market_data_collect_5m", "market_data_service_fetch_ohlcv", "gate_spot_candlesticks_url", "gate_market_data_parse_gate_spot_candle", "pg_table_ohlcv", "ohlcv_metrics_prometheus"],
      "relation": "participate_in",
      "confidence": "EXTRACTED",
      "confidence_score": 1.0,
      "source_file": "backend/app/tasks/collect_market_data.py"
    },
    {
      "id": "order_flow_data_path",
      "label": "Order Flow Data Path: WS buffer (primary) → REST fallback → taker_ratio computation",
      "nodes": ["redis_key_trades_buffer", "order_flow_service_read_buffer", "order_flow_service_rest_fallback", "order_flow_service_safe_taker_ratio", "order_flow_service_aggregate_buy_sell", "order_flow_service_handover_taint"],
      "relation": "participate_in",
      "confidence": "EXTRACTED",
      "confidence_score": 1.0,
      "source_file": "backend/app/services/order_flow_service.py"
    },
    {
      "id": "robust_indicator_scoring_chain",
      "label": "Robust Indicator Scoring Chain: envelope_indicators → validate → calculate_score_with_confidence → persist_snapshot",
      "nodes": ["robust_indicators_envelope_fn", "robust_indicators_envelope", "robust_indicators_confidence_map", "robust_indicators_staleness_penalty", "robust_indicators_validation", "robust_indicators_score", "robust_indicators_snapshot_table"],
      "relation": "implement",
      "confidence": "EXTRACTED",
      "confidence_score": 1.0,
      "source_file": "backend/app/services/robust_indicators/compute.py"
    },
    {
      "id": "futures_scanner_5layer_scoring",
      "label": "Futures Scanner 5-Layer Scoring: L1 Liquidity + L2 Structure + L3 Momentum + L4 Volatility + L5 OrderFlow",
      "nodes": ["futures_scanner_l1_liquidity", "futures_scanner_l2_structure", "futures_scanner_l3_momentum", "futures_scanner_l4_volatility", "futures_scanner_l5_order_flow", "futures_scanner_gate3_min_score"],
      "relation": "implement",
      "confidence": "EXTRACTED",
      "confidence_score": 1.0,
      "source_file": "backend/app/engines/futures_scanner.py"
    },
    {
      "id": "market_metadata_anti_deadlock",
      "label": "market_metadata Anti-Deadlock: sorted-symbol UPSERT across collect_all + collect_5m + fallback paths",
      "nodes": ["collect_market_data_bulk_upsert_market_metadata", "collect_market_data_collect_all", "collect_market_data_collect_5m", "collect_market_data_stale_volume_fallback", "pg_table_market_metadata"],
      "relation": "participate_in",
      "confidence": "EXTRACTED",
      "confidence_score": 1.0,
      "source_file": "backend/app/tasks/collect_market_data.py"
    },
    {
      "id": "pipeline_l3_live_flow_gate",
      "label": "Pipeline L3 Live Flow Gate: staleness check (data_age_seconds ≤ 15s) before order flow injection",
      "nodes": ["pipeline_scan_live_order_flow_injection", "pipeline_scan_order_flow_window", "pipeline_scan_order_flow_max_age", "order_flow_service_get_order_flow_data", "redis_key_trades_buffer"],
      "relation": "implement",
      "confidence": "EXTRACTED",
      "confidence_score": 1.0,
      "source_file": "backend/app/tasks/pipeline_scan.py"
    },
    {
      "id": "ohlcv_data_source_fallback_chain",
      "label": "OHLCV Data Source Fallback Chain: Gate.io primary (≥50 candles) → Binance fallback → merged deduplicated DataFrame",
      "nodes": ["market_data_service_fetch_ohlcv", "gate_spot_candlesticks_url", "market_data_service_min_ohlcv_candles", "market_data_service_class"],
      "relation": "implement",
      "confidence": "EXTRACTED",
      "confidence_score": 1.0,
      "source_file": "backend/app/services/market_data_service.py"
    },
    {
      "id": "indicator_freshness_quality_system",
      "label": "Indicator Freshness/Quality System: STALENESS_PENALTY + CONFIDENCE_MAP + can_trade gating",
      "nodes": ["robust_indicators_staleness_penalty", "robust_indicators_confidence_map", "robust_indicators_can_trade_threshold", "robust_indicators_envelope", "robust_indicators_metrics"],
      "relation": "form",
      "confidence": "EXTRACTED",
      "confidence_score": 1.0,
      "source_file": "backend/app/services/robust_indicators/envelope.py"
    }
  ],
  "input_tokens": 0,
  "output_tokens": 0
}
