[
  {
    "textPayload": "Traceback (most recent call last):\n  File \"/usr/local/lib/python3.12/site-packages/sqlalchemy/pool/base.py\", line 373, in _close_connection\n    self._dialect.do_terminate(connection)\n  File \"/usr/local/lib/python3.12/site-packages/sqlalchemy/dialects/postgresql/asyncpg.py\", line 1127, in do_terminate\n    dbapi_connection.terminate()\n  File \"/usr/local/lib/python3.12/site-packages/sqlalchemy/connectors/asyncio.py\", line 402, in terminate\n    self.await_(asyncio.shield(self._terminate_graceful_close()))  # type: ignore[attr-defined] # noqa: E501\n    ^^^^^^^^^^^^^^^^^^^^^^^^^^^^^^^^^^^^^^^^^^^^^^^^^^^^^^^^^^^^^\n  File \"/usr/local/lib/python3.12/site-packages/sqlalchemy/util/_concurrency_py3k.py\", line 132, in await_only\n    return current.parent.switch(awaitable)  # type: ignore[no-any-return,attr-defined] # noqa: E501\n           ^^^^^^^^^^^^^^^^^^^^^^^^^^^^^^^^\n  File \"/usr/local/lib/python3.12/site-packages/sqlalchemy/util/_concurrency_py3k.py\", line 196, in greenlet_spawn\n    value = await result\n            ^^^^^^^^^^^^\n  File \"/usr/local/lib/python3.12/site-packages/sqlalchemy/dialects/postgresql/asyncpg.py\", line 912, in _terminate_graceful_close\n    await self._connection.close(timeout=2)\n  File \"/usr/local/lib/python3.12/site-packages/asyncpg/connection.py\", line 1513, in close\n    await self._protocol.close(timeout)\n  File \"asyncpg/protocol/protocol.pyx\", line 617, in close\n  File \"asyncpg/protocol/protocol.pyx\", line 650, in asyncpg.protocol.protocol.BaseProtocol._request_cancel\n  File \"/usr/local/lib/python3.12/site-packages/asyncpg/connection.py\", line 1682, in _cancel_current_command\n    self._cancellations.add(self._loop.create_task(self._cancel(waiter)))\n                            ^^^^^^^^^^^^^^^^^^^^^^^^^^^^^^^^^^^^^^^^^^^^\n  File \"/usr/local/lib/python3.12/asyncio/base_events.py\", line 455, in create_task\n    self._check_closed()\n  File \"/usr/local/lib/python3.12/asyncio/base_events.py\", line 545, in _check_closed\n    raise RuntimeError('Event loop is closed')\nRuntimeError: Event loop is closed",
    "insertId": "69fce5ee000ee03fc5df1453",
    "resource": {
      "type": "cloud_run_revision",
      "labels": {
        "revision_name": "scalpyn-00442-dbs",
        "configuration_name": "scalpyn",
        "project_id": "clickrate-477217",
        "location": "us-central1",
        "service_name": "scalpyn"
      }
    },
    "timestamp": "2026-05-07T19:20:14.974911Z",
    "severity": "ERROR",
    "labels": {
      "managed-by": "gcp-cloud-build-deploy-cloud-run",
      "instanceId": "0007b734d92e0ee16d42fb79b4a3408a09cb02135b7be9aaafaa614ba0e985916b2944c7cc0e60ebb281c28df7962fc1dc3fd1ff850d25d4b47cd52823302b33511992f19030219bae5b3291b4ef",
      "gcb-trigger-region": "global",
      "gcb-trigger-id": "806f4336-706a-404f-82be-dd0d5c01ebfa",
      "commit-sha": "2800521f9db260bdc42c47fcafb01226b950df4a",
      "gcb-build-id": "7e0bb172-2c6d-416d-b487-ea69b3b95288"
    },
    "logName": "projects/clickrate-477217/logs/run.googleapis.com%2Fstderr",
    "receiveTimestamp": "2026-05-07T19:20:15.155875861Z",
    "errorGroups": [
      {
        "id": "CIaUi4fY3-nCJw"
      }
    ]
  },
  {
    "textPayload": "Container called exit(0).",
    "insertId": "69fce603000a0c75fac0e922",
    "resource": {
      "type": "cloud_run_revision",
      "labels": {
        "location": "us-central1",
        "service_name": "scalpyn-worker-execution",
        "configuration_name": "scalpyn-worker-execution",
        "revision_name": "scalpyn-worker-execution-00001-mfr",
        "project_id": "clickrate-477217"
      }
    },
    "timestamp": "2026-05-07T19:20:35.658356Z",
    "severity": "WARNING",
    "labels": {
      "gcb-trigger-region": "global",
      "managed-by": "gcp-cloud-build-deploy-cloud-run",
      "instanceId": "0007b734d949c6f419a6be6bb2cb70c15d1f12491f55fd3412e5cf8bbfe9409c37d630f67c051011863ffa9a3e7aac5826c714f43030cae19eee3b03cad015f0e3f1b4948d63651773ccbc0d2d29",
      "container_name": "placeholder-1",
      "gcb-build-id": "7e0bb172-2c6d-416d-b487-ea69b3b95288",
      "gcb-trigger-id": "806f4336-706a-404f-82be-dd0d5c01ebfa",
      "commit-sha": "2800521f9db260bdc42c47fcafb01226b950df4a"
    },
    "logName": "projects/clickrate-477217/logs/run.googleapis.com%2Fvarlog%2Fsystem",
    "receiveTimestamp": "2026-05-07T19:20:35.664064075Z"
  },
  {
    "textPayload": "Container called exit(0).",
    "insertId": "69fce6220007b4e46cf816af",
    "resource": {
      "type": "cloud_run_revision",
      "labels": {
        "project_id": "clickrate-477217",
        "configuration_name": "scalpyn-beat",
        "revision_name": "scalpyn-beat-00001-lz4",
        "service_name": "scalpyn-beat",
        "location": "us-central1"
      }
    },
    "timestamp": "2026-05-07T19:21:06.504911Z",
    "severity": "WARNING",
    "labels": {
      "gcb-trigger-id": "806f4336-706a-404f-82be-dd0d5c01ebfa",
      "commit-sha": "2800521f9db260bdc42c47fcafb01226b950df4a",
      "container_name": "placeholder-1",
      "gcb-build-id": "7e0bb172-2c6d-416d-b487-ea69b3b95288",
      "instanceId": "0007b734d92a1a08aad8f0d33f58122f15972e9d48073a30c673bbe4c56c285dcfc3d5057a36712ca77ca4f8a5093af693549f0f7428570c4453993d6d2d659e83e4095d966b9d8b546825727ab4",
      "managed-by": "gcp-cloud-build-deploy-cloud-run",
      "gcb-trigger-region": "global"
    },
    "logName": "projects/clickrate-477217/logs/run.googleapis.com%2Fvarlog%2Fsystem",
    "receiveTimestamp": "2026-05-07T19:21:06.512911186Z"
  },
  {
    "textPayload": "Traceback (most recent call last):\n  File \"/usr/local/lib/python3.12/site-packages/sqlalchemy/pool/base.py\", line 373, in _close_connection\n    self._dialect.do_terminate(connection)\n  File \"/usr/local/lib/python3.12/site-packages/sqlalchemy/dialects/postgresql/asyncpg.py\", line 1127, in do_terminate\n    dbapi_connection.terminate()\n  File \"/usr/local/lib/python3.12/site-packages/sqlalchemy/connectors/asyncio.py\", line 402, in terminate\n    self.await_(asyncio.shield(self._terminate_graceful_close()))  # type: ignore[attr-defined] # noqa: E501\n    ^^^^^^^^^^^^^^^^^^^^^^^^^^^^^^^^^^^^^^^^^^^^^^^^^^^^^^^^^^^^^\n  File \"/usr/local/lib/python3.12/site-packages/sqlalchemy/util/_concurrency_py3k.py\", line 132, in await_only\n    return current.parent.switch(awaitable)  # type: ignore[no-any-return,attr-defined] # noqa: E501\n           ^^^^^^^^^^^^^^^^^^^^^^^^^^^^^^^^\n  File \"/usr/local/lib/python3.12/site-packages/sqlalchemy/util/_concurrency_py3k.py\", line 196, in greenlet_spawn\n    value = await result\n            ^^^^^^^^^^^^\n  File \"/usr/local/lib/python3.12/site-packages/sqlalchemy/dialects/postgresql/asyncpg.py\", line 912, in _terminate_graceful_close\n    await self._connection.close(timeout=2)\n  File \"/usr/local/lib/python3.12/site-packages/asyncpg/connection.py\", line 1513, in close\n    await self._protocol.close(timeout)\n  File \"asyncpg/protocol/protocol.pyx\", line 617, in close\n  File \"asyncpg/protocol/protocol.pyx\", line 650, in asyncpg.protocol.protocol.BaseProtocol._request_cancel\n  File \"/usr/local/lib/python3.12/site-packages/asyncpg/connection.py\", line 1682, in _cancel_current_command\n    self._cancellations.add(self._loop.create_task(self._cancel(waiter)))\n                            ^^^^^^^^^^^^^^^^^^^^^^^^^^^^^^^^^^^^^^^^^^^^\n  File \"/usr/local/lib/python3.12/asyncio/base_events.py\", line 455, in create_task\n    self._check_closed()\n  File \"/usr/local/lib/python3.12/asyncio/base_events.py\", line 545, in _check_closed\n    raise RuntimeError('Event loop is closed')\nRuntimeError: Event loop is closed",
    "insertId": "69fce62a000ec314f127672b",
    "resource": {
      "type": "cloud_run_revision",
      "labels": {
        "revision_name": "scalpyn-00442-dbs",
        "configuration_name": "scalpyn",
        "project_id": "clickrate-477217",
        "location": "us-central1",
        "service_name": "scalpyn"
      }
    },
    "timestamp": "2026-05-07T19:21:14.967444Z",
    "severity": "ERROR",
    "labels": {
      "gcb-build-id": "7e0bb172-2c6d-416d-b487-ea69b3b95288",
      "gcb-trigger-id": "806f4336-706a-404f-82be-dd0d5c01ebfa",
      "commit-sha": "2800521f9db260bdc42c47fcafb01226b950df4a",
      "gcb-trigger-region": "global",
      "instanceId": "0007b734d92e0ee16d42fb79b4a3408a09cb02135b7be9aaafaa614ba0e985916b2944c7cc0e60ebb281c28df7962fc1dc3fd1ff850d25d4b47cd52823302b33511992f19030219bae5b3291b4ef",
      "managed-by": "gcp-cloud-build-deploy-cloud-run"
    },
    "logName": "projects/clickrate-477217/logs/run.googleapis.com%2Fstderr",
    "receiveTimestamp": "2026-05-07T19:21:15.099477095Z",
    "errorGroups": [
      {
        "id": "CIaUi4fY3-nCJw"
      }
    ]
  },
  {
    "textPayload": "The request failed because either the HTTP response was malformed or connection to the instance had an error. Additional troubleshooting documentation can be found at: https://cloud.google.com/run/docs/troubleshooting#malformed-response-or-connection-error",
    "insertId": "69fce63c000dea0fa9c4ba92",
    "httpRequest": {
      "requestMethod": "POST",
      "requestUrl": "https://scalpyn-wm56dfqgta-uc.a.run.app/api/auth/login",
      "requestSize": "516",
      "status": 503,
      "responseSize": "67",
      "userAgent": "Deno/2.1.4 (variant; SupabaseEdgeRuntime/1.74.0)",
      "remoteIp": "2a05:d018:1a8b:4004:52f5:eae9:9ca5:7d93",
      "serverIp": "2600:1900:4244:200::",
      "latency": "0.389817358s",
      "protocol": "HTTP/1.1"
    },
    "resource": {
      "type": "cloud_run_revision",
      "labels": {
        "project_id": "clickrate-477217",
        "revision_name": "scalpyn-00442-dbs",
        "configuration_name": "scalpyn",
        "location": "us-central1",
        "service_name": "scalpyn"
      }
    },
    "timestamp": "2026-05-07T19:21:32.520120Z",
    "severity": "ERROR",
    "labels": {
      "gcb-trigger-region": "global",
      "instanceId": "0007b734d92e0ee16d42fb79b4a3408a09cb02135b7be9aaafaa614ba0e985916b2944c7cc0e60ebb281c28df7962fc1dc3fd1ff850d25d4b47cd52823302b33511992f19030219bae5b3291b4ef",
      "managed-by": "gcp-cloud-build-deploy-cloud-run",
      "gcb-build-id": "7e0bb172-2c6d-416d-b487-ea69b3b95288",
      "gcb-trigger-id": "806f4336-706a-404f-82be-dd0d5c01ebfa",
      "commit-sha": "2800521f9db260bdc42c47fcafb01226b950df4a"
    },
    "logName": "projects/clickrate-477217/logs/run.googleapis.com%2Frequests",
    "trace": "projects/clickrate-477217/traces/4278affdde51785f03941b7f279f47a5",
    "receiveTimestamp": "2026-05-07T19:21:33.168367227Z",
    "spanId": "6fe40f1e050b9c04",
    "traceSampled": true
  },
  {
    "textPayload": "Container called exit(0).",
    "insertId": "69fce650000a0beed868b6d0",
    "resource": {
      "type": "cloud_run_revision",
      "labels": {
        "service_name": "scalpyn-worker-micro",
        "location": "us-central1",
        "revision_name": "scalpyn-worker-micro-00001-fpm",
        "configuration_name": "scalpyn-worker-micro",
        "project_id": "clickrate-477217"
      }
    },
    "timestamp": "2026-05-07T19:21:52.658382Z",
    "severity": "WARNING",
    "labels": {
      "managed-by": "gcp-cloud-build-deploy-cloud-run",
      "instanceId": "0007b734d9320eb05d515cb778f24327ac1c3bac6e51a7c748f993bfc7bb58fef5f56c53a54fef330ea91d34cd1d2dbee9c780265ec411ed7808bd6e7495c2d75afcb174e7de64d45af06b892cd9",
      "gcb-trigger-region": "global",
      "gcb-trigger-id": "806f4336-706a-404f-82be-dd0d5c01ebfa",
      "commit-sha": "2800521f9db260bdc42c47fcafb01226b950df4a",
      "container_name": "placeholder-1",
      "gcb-build-id": "7e0bb172-2c6d-416d-b487-ea69b3b95288"
    },
    "logName": "projects/clickrate-477217/logs/run.googleapis.com%2Fvarlog%2Fsystem",
    "receiveTimestamp": "2026-05-07T19:21:52.666080863Z"
  },
  {
    "textPayload": "2026-05-07 19:22:12.441 UTC [287721]: [1-1] db=scalpyn,user=postgres,host=[local] ERROR:  canceling statement due to user request",
    "insertId": "s=8cc2e3eb994f443caf665154fcf6b2d8;i=14efce;b=611034922472440d996701ab4475db58;m=3b196f2712;t=6513f2fff66f3;x=8b8ca9cfb56f536f-0@a4",
    "resource": {
      "type": "cloudsql_database",
      "labels": {
        "database_id": "clickrate-477217:scalpyn",
        "region": "us-central",
        "project_id": "clickrate-477217"
      }
    },
    "timestamp": "2026-05-07T19:22:12.441442Z",
    "severity": "ERROR",
    "labels": {
      "LOG_BUCKET_NUM": "55",
      "SOURCE_ID": "37333130396234346565326662666435e3b0c442",
      "INSTANCE_UID": "1-e1be44ec-f7ea-4e99-b2e1-4845aa2b37a7",
      "PROJECT_NUMBER": "330575088921"
    },
    "logName": "projects/clickrate-477217/logs/cloudsql.googleapis.com%2Fpostgres.log",
    "receiveTimestamp": "2026-05-07T19:22:24.922792058Z"
  },
  {
    "textPayload": "2026-05-07 19:22:12.449 UTC [287725]: [1-1] db=scalpyn,user=postgres,host=[local] ERROR:  canceling statement due to user request",
    "insertId": "s=8cc2e3eb994f443caf665154fcf6b2d8;i=14efce;b=611034922472440d996701ab4475db58;m=3b196f2712;t=6513f2fff66f3;x=8b8ca9cfb56f536f-0@a7",
    "resource": {
      "type": "cloudsql_database",
      "labels": {
        "project_id": "clickrate-477217",
        "database_id": "clickrate-477217:scalpyn",
        "region": "us-central"
      }
    },
    "timestamp": "2026-05-07T19:22:12.449440Z",
    "severity": "ERROR",
    "labels": {
      "LOG_BUCKET_NUM": "55",
      "PROJECT_NUMBER": "330575088921",
      "SOURCE_ID": "37333130396234346565326662666435e3b0c442",
      "INSTANCE_UID": "1-e1be44ec-f7ea-4e99-b2e1-4845aa2b37a7"
    },
    "logName": "projects/clickrate-477217/logs/cloudsql.googleapis.com%2Fpostgres.log",
    "receiveTimestamp": "2026-05-07T19:22:24.922792058Z"
  },
  {
    "textPayload": "2026-05-07 19:22:16.207 UTC [287803]: [2-1] db=scalpyn,user=postgres,host=[local] FATAL:  connection to client lost",
    "insertId": "s=8cc2e3eb994f443caf665154fcf6b2d8;i=14efce;b=611034922472440d996701ab4475db58;m=3b196f2712;t=6513f2fff66f3;x=8b8ca9cfb56f536f-0@ab",
    "resource": {
      "type": "cloudsql_database",
      "labels": {
        "project_id": "clickrate-477217",
        "database_id": "clickrate-477217:scalpyn",
        "region": "us-central"
      }
    },
    "timestamp": "2026-05-07T19:22:16.208346Z",
    "severity": "ALERT",
    "labels": {
      "LOG_BUCKET_NUM": "55",
      "PROJECT_NUMBER": "330575088921",
      "INSTANCE_UID": "1-e1be44ec-f7ea-4e99-b2e1-4845aa2b37a7",
      "SOURCE_ID": "37333130396234346565326662666435e3b0c442"
    },
    "logName": "projects/clickrate-477217/logs/cloudsql.googleapis.com%2Fpostgres.log",
    "receiveTimestamp": "2026-05-07T19:22:24.922792058Z"
  },
  {
    "textPayload": "2026-05-07 19:22:24.377 UTC [287703]: [2-1] db=scalpyn,user=postgres,host=[local] FATAL:  connection to client lost",
    "insertId": "s=8cc2e3eb994f443caf665154fcf6b2d8;i=14efce;b=611034922472440d996701ab4475db58;m=3b196f2712;t=6513f2fff66f3;x=8b8ca9cfb56f536f-0@af",
    "resource": {
      "type": "cloudsql_database",
      "labels": {
        "project_id": "clickrate-477217",
        "database_id": "clickrate-477217:scalpyn",
        "region": "us-central"
      }
    },
    "timestamp": "2026-05-07T19:22:24.379222Z",
    "severity": "ALERT",
    "labels": {
      "LOG_BUCKET_NUM": "55",
      "PROJECT_NUMBER": "330575088921",
      "INSTANCE_UID": "1-e1be44ec-f7ea-4e99-b2e1-4845aa2b37a7",
      "SOURCE_ID": "37333130396234346565326662666435e3b0c442"
    },
    "logName": "projects/clickrate-477217/logs/cloudsql.googleapis.com%2Fpostgres.log",
    "receiveTimestamp": "2026-05-07T19:22:24.922792058Z"
  },
  {
    "textPayload": "2026-05-07 19:22:24.379 UTC [287704]: [2-1] db=scalpyn,user=postgres,host=[local] FATAL:  connection to client lost",
    "insertId": "s=8cc2e3eb994f443caf665154fcf6b2d8;i=14f05f;b=611034922472440d996701ab4475db58;m=3b1ca806c7;t=6513f333846a7;x=2072e089668ee804-0@a2",
    "resource": {
      "type": "cloudsql_database",
      "labels": {
        "region": "us-central",
        "database_id": "clickrate-477217:scalpyn",
        "project_id": "clickrate-477217"
      }
    },
    "timestamp": "2026-05-07T19:22:24.379634Z",
    "severity": "ALERT",
    "labels": {
      "LOG_BUCKET_NUM": "55",
      "PROJECT_NUMBER": "330575088921",
      "INSTANCE_UID": "1-e1be44ec-f7ea-4e99-b2e1-4845aa2b37a7",
      "SOURCE_ID": "37333130396234346565326662666435e3b0c442"
    },
    "logName": "projects/clickrate-477217/logs/cloudsql.googleapis.com%2Fpostgres.log",
    "receiveTimestamp": "2026-05-07T19:22:26.461282262Z"
  },
  {
    "textPayload": "Container called exit(0).",
    "insertId": "69fce67000063da4e06dd643",
    "resource": {
      "type": "cloud_run_revision",
      "labels": {
        "location": "us-central1",
        "service_name": "scalpyn-worker-structural",
        "project_id": "clickrate-477217",
        "configuration_name": "scalpyn-worker-structural",
        "revision_name": "scalpyn-worker-structural-00001-pjm"
      }
    },
    "timestamp": "2026-05-07T19:22:24.408888Z",
    "severity": "WARNING",
    "labels": {
      "gcb-trigger-id": "806f4336-706a-404f-82be-dd0d5c01ebfa",
      "commit-sha": "2800521f9db260bdc42c47fcafb01226b950df4a",
      "container_name": "placeholder-1",
      "gcb-build-id": "7e0bb172-2c6d-416d-b487-ea69b3b95288",
      "instanceId": "0007b734d9f749617f2274a80e7c3e7d434f76271af3e0442c1d1cfeae9d27c9ac3ec87d65ba5c47edcc11db60b4f9627b3c06fb86ee17dfcc88f3cdce1abb0cbca2fe570ad7f2d37726adaf12a275",
      "managed-by": "gcp-cloud-build-deploy-cloud-run",
      "gcb-trigger-region": "global"
    },
    "logName": "projects/clickrate-477217/logs/run.googleapis.com%2Fvarlog%2Fsystem",
    "receiveTimestamp": "2026-05-07T19:22:24.415184111Z"
  },
  {
    "textPayload": "2026-05-07 19:23:01.559 UTC [287685]: [1-1] db=scalpyn,user=postgres,host=[local] ERROR:  canceling statement due to user request",
    "insertId": "s=8cc2e3eb994f443caf665154fcf6b2d8;i=14f063;b=611034922472440d996701ab4475db58;m=3b1cbc61d1;t=6513f334ca1b2;x=cff1708be9c1e2a7-0@a5",
    "resource": {
      "type": "cloudsql_database",
      "labels": {
        "database_id": "clickrate-477217:scalpyn",
        "region": "us-central",
        "project_id": "clickrate-477217"
      }
    },
    "timestamp": "2026-05-07T19:23:01.560561Z",
    "severity": "ERROR",
    "labels": {
      "PROJECT_NUMBER": "330575088921",
      "INSTANCE_UID": "1-e1be44ec-f7ea-4e99-b2e1-4845aa2b37a7",
      "SOURCE_ID": "37333130396234346565326662666435e3b0c442",
      "LOG_BUCKET_NUM": "55"
    },
    "logName": "projects/clickrate-477217/logs/cloudsql.googleapis.com%2Fpostgres.log",
    "receiveTimestamp": "2026-05-07T19:23:02.839130204Z"
  },
  {
    "textPayload": "Traceback (most recent call last):\n  File \"/app/app/services/microstructure_scheduler_service.py\", line 267, in _refresh_market_metadata\n    await db.execute(text(\"\"\"\n  File \"/usr/local/lib/python3.12/site-packages/sqlalchemy/ext/asyncio/session.py\", line 449, in execute\n    result = await greenlet_spawn(\n             ^^^^^^^^^^^^^^^^^^^^^\n  File \"/usr/local/lib/python3.12/site-packages/sqlalchemy/util/_concurrency_py3k.py\", line 203, in greenlet_spawn\n    result = context.switch(value)\n             ^^^^^^^^^^^^^^^^^^^^^\n  File \"/usr/local/lib/python3.12/site-packages/sqlalchemy/orm/session.py\", line 2351, in execute\n    return self._execute_internal(\n           ^^^^^^^^^^^^^^^^^^^^^^^\n  File \"/usr/local/lib/python3.12/site-packages/sqlalchemy/orm/session.py\", line 2258, in _execute_internal\n    result = conn.execute(\n             ^^^^^^^^^^^^^\n  File \"/usr/local/lib/python3.12/site-packages/sqlalchemy/engine/base.py\", line 1419, in execute\n    return meth(\n           ^^^^^\n  File \"/usr/local/lib/python3.12/site-packages/sqlalchemy/sql/elements.py\", line 527, in _execute_on_connection\n    return connection._execute_clauseelement(\n           ^^^^^^^^^^^^^^^^^^^^^^^^^^^^^^^^^^\n  File \"/usr/local/lib/python3.12/site-packages/sqlalchemy/engine/base.py\", line 1641, in _execute_clauseelement\n    ret = self._execute_context(\n          ^^^^^^^^^^^^^^^^^^^^^^\n  File \"/usr/local/lib/python3.12/site-packages/sqlalchemy/engine/base.py\", line 1846, in _execute_context\n    return self._exec_single_context(\n           ^^^^^^^^^^^^^^^^^^^^^^^^^^\n  File \"/usr/local/lib/python3.12/site-packages/sqlalchemy/engine/base.py\", line 1986, in _exec_single_context\n    self._handle_dbapi_exception(\n  File \"/usr/local/lib/python3.12/site-packages/sqlalchemy/engine/base.py\", line 2366, in _handle_dbapi_exception\n    raise exc_info[1].with_traceback(exc_info[2])\n  File \"/usr/local/lib/python3.12/site-packages/sqlalchemy/engine/base.py\", line 1967, in _exec_single_context\n    self.dialect.do_execute(\n  File \"/usr/local/lib/python3.12/site-packages/sqlalchemy/engine/default.py\", line 952, in do_execute\n    cursor.execute(statement, parameters)\n  File \"/usr/local/lib/python3.12/site-packages/sqlalchemy/dialects/postgresql/asyncpg.py\", line 585, in execute\n    self._adapt_connection.await_(\n  File \"/usr/local/lib/python3.12/site-packages/sqlalchemy/util/_concurrency_py3k.py\", line 132, in await_only\n    return current.parent.switch(awaitable)  # type: ignore[no-any-return,attr-defined] # noqa: E501\n           ^^^^^^^^^^^^^^^^^^^^^^^^^^^^^^^^\n  File \"/usr/local/lib/python3.12/site-packages/sqlalchemy/util/_concurrency_py3k.py\", line 196, in greenlet_spawn\n    value = await result\n            ^^^^^^^^^^^^\n  File \"/usr/local/lib/python3.12/site-packages/sqlalchemy/dialects/postgresql/asyncpg.py\", line 563, in _prepare_and_execute\n    self._handle_exception(error)\n  File \"/usr/local/lib/python3.12/site-packages/sqlalchemy/dialects/postgresql/asyncpg.py\", line 513, in _handle_exception\n    self._adapt_connection._handle_exception(error)\n  File \"/usr/local/lib/python3.12/site-packages/sqlalchemy/dialects/postgresql/asyncpg.py\", line 799, in _handle_exception\n    raise error\n  File \"/usr/local/lib/python3.12/site-packages/sqlalchemy/dialects/postgresql/asyncpg.py\", line 550, in _prepare_and_execute\n    self._rows = deque(await prepared_stmt.fetch(*parameters))\n                       ^^^^^^^^^^^^^^^^^^^^^^^^^^^^^^^^^^^^^^\n  File \"/usr/local/lib/python3.12/site-packages/asyncpg/prepared_stmt.py\", line 177, in fetch\n    data = await self.__bind_execute(args, 0, timeout)\n           ^^^^^^^^^^^^^^^^^^^^^^^^^^^^^^^^^^^^^^^^^^^\n  File \"/usr/local/lib/python3.12/site-packages/asyncpg/prepared_stmt.py\", line 268, in __bind_execute\n    data, status, _ = await self.__do_execute(\n                      ^^^^^^^^^^^^^^^^^^^^^^^^\n  File \"/usr/local/lib/python3.12/site-packages/asyncpg/prepared_stmt.py\", line 257, in __do_execute\n    return await executor(protocol)\n           ^^^^^^^^^^^^^^^^^^^^^^^^\n  File \"asyncpg/protocol/protocol.pyx\", line 205, in bind_execute",
    "insertId": "69fce69500096028f73442dd",
    "resource": {
      "type": "cloud_run_revision",
      "labels": {
        "project_id": "clickrate-477217",
        "revision_name": "scalpyn-00443-w7q",
        "configuration_name": "scalpyn",
        "location": "us-central1",
        "service_name": "scalpyn"
      }
    },
    "timestamp": "2026-05-07T19:23:01.614440Z",
    "severity": "ERROR",
    "labels": {
      "gcb-trigger-region": "global",
      "managed-by": "gcp-cloud-build-deploy-cloud-run",
      "instanceId": "0007b734d9a62281d226db90aee11253f4c315f280c79275243d7397d7a72c25d2df44286354750d38ca5d7a4646bb2cb2d633f3611c60772c6af764b9b75ff4e69e0f892501e10848cc24122ed74c",
      "gcb-build-id": "262efc38-54bb-4063-9b69-4ad1e03943b1",
      "commit-sha": "f8c801f7afc98c5489a805be516f9814ad7963bc",
      "gcb-trigger-id": "806f4336-706a-404f-82be-dd0d5c01ebfa"
    },
    "logName": "projects/clickrate-477217/logs/run.googleapis.com%2Fstderr",
    "receiveTimestamp": "2026-05-07T19:23:01.897849771Z",
    "errorGroups": [
      {
        "id": "CPWDqLSKh4CnuAE"
      }
    ]
  },
  {
    "textPayload": "Container called exit(0).",
    "insertId": "69fce6a8000d347fee1cd48e",
    "resource": {
      "type": "cloud_run_revision",
      "labels": {
        "location": "us-central1",
        "service_name": "scalpyn-worker-execution",
        "configuration_name": "scalpyn-worker-execution",
        "revision_name": "scalpyn-worker-execution-00001-mfr",
        "project_id": "clickrate-477217"
      }
    },
    "timestamp": "2026-05-07T19:23:20.865329Z",
    "severity": "WARNING",
    "labels": {
      "gcb-build-id": "7e0bb172-2c6d-416d-b487-ea69b3b95288",
      "container_name": "placeholder-1",
      "commit-sha": "2800521f9db260bdc42c47fcafb01226b950df4a",
      "gcb-trigger-id": "806f4336-706a-404f-82be-dd0d5c01ebfa",
      "gcb-trigger-region": "global",
      "instanceId": "0007b734d97f2b4f2890ba64e9f883c8b26f233f1ad3f218aeae4d4dc81bd82cc28726c0c963f07fa275e05a471892d32ef3c8fc5780d79a6c0e232e31403794fb002c6aefd09f5376459ef0c0c0",
      "managed-by": "gcp-cloud-build-deploy-cloud-run"
    },
    "logName": "projects/clickrate-477217/logs/run.googleapis.com%2Fvarlog%2Fsystem",
    "receiveTimestamp": "2026-05-07T19:23:20.874097359Z"
  },
  {
    "textPayload": "2026-05-07 19:23:31.720 UTC [287877]: [1-1] db=scalpyn,user=postgres,host=[local] ERROR:  canceling statement due to user request",
    "insertId": "s=8cc2e3eb994f443caf665154fcf6b2d8;i=14f0c7;b=611034922472440d996701ab4475db58;m=3b1ef06901;t=6513f3580a8e2;x=3a64afe1537af80b-0@a7",
    "resource": {
      "type": "cloudsql_database",
      "labels": {
        "project_id": "clickrate-477217",
        "region": "us-central",
        "database_id": "clickrate-477217:scalpyn"
      }
    },
    "timestamp": "2026-05-07T19:23:31.720813Z",
    "severity": "ERROR",
    "labels": {
      "LOG_BUCKET_NUM": "55",
      "PROJECT_NUMBER": "330575088921",
      "INSTANCE_UID": "1-e1be44ec-f7ea-4e99-b2e1-4845aa2b37a7",
      "SOURCE_ID": "37333130396234346565326662666435e3b0c442"
    },
    "logName": "projects/clickrate-477217/logs/cloudsql.googleapis.com%2Fpostgres.log",
    "receiveTimestamp": "2026-05-07T19:23:32.548967741Z"
  },
  {
    "textPayload": "Traceback (most recent call last):\n  File \"/usr/local/lib/python3.12/site-packages/celery/app/trace.py\", line 585, in trace_task\n    R = retval = fun(*args, **kwargs)\n                 ^^^^^^^^^^^^^^^^^^^^\n  File \"/usr/local/lib/python3.12/site-packages/celery/app/trace.py\", line 858, in __protected_call__\n    return self.run(*args, **kwargs)\n           ^^^^^^^^^^^^^^^^^^^^^^^^^\n  File \"/app/app/tasks/compute_indicators.py\", line 407, in compute\n    count = _run_async(_compute_async())\n            ^^^^^^^^^^^^^^^^^^^^^^^^^^^^\n  File \"/app/app/tasks/compute_indicators.py\", line 157, in _run_async\n    return loop.run_until_complete(coro)\n           ^^^^^^^^^^^^^^^^^^^^^^^^^^^^^\n  File \"/usr/local/lib/python3.12/asyncio/base_events.py\", line 691, in run_until_complete\n    return future.result()\n           ^^^^^^^^^^^^^^^\n  File \"/app/app/tasks/compute_indicators.py\", line 395, in _compute_async\n    await db.commit()\n  File \"/usr/local/lib/python3.12/site-packages/sqlalchemy/ext/asyncio/session.py\", line 1000, in commit\n    await greenlet_spawn(self.sync_session.commit)\n  File \"/usr/local/lib/python3.12/site-packages/sqlalchemy/util/_concurrency_py3k.py\", line 190, in greenlet_spawn\n    result = context.switch(*args, **kwargs)\n             ^^^^^^^^^^^^^^^^^^^^^^^^^^^^^^^\n  File \"/usr/local/lib/python3.12/site-packages/sqlalchemy/orm/session.py\", line 2030, in commit\n    trans.commit(_to_root=True)\n  File \"<string>\", line 2, in commit\n  File \"/usr/local/lib/python3.12/site-packages/sqlalchemy/orm/state_changes.py\", line 137, in _go\n    ret_value = fn(self, *arg, **kw)\n                ^^^^^^^^^^^^^^^^^^^^\n  File \"/usr/local/lib/python3.12/site-packages/sqlalchemy/orm/session.py\", line 1318, in commit\n    trans.commit()\n  File \"/usr/local/lib/python3.12/site-packages/sqlalchemy/engine/base.py\", line 2640, in commit\n    self._do_commit()\n  File \"/usr/local/lib/python3.12/site-packages/sqlalchemy/engine/base.py\", line 2745, in _do_commit\n    self._connection_commit_impl()\n  File \"/usr/local/lib/python3.12/site-packages/sqlalchemy/engine/base.py\", line 2716, in _connection_commit_impl\n    self.connection._commit_impl()\n  File \"/usr/local/lib/python3.12/site-packages/sqlalchemy/engine/base.py\", line 1147, in _commit_impl\n    self._handle_dbapi_exception(e, None, None, None, None)\n  File \"/usr/local/lib/python3.12/site-packages/sqlalchemy/engine/base.py\", line 2366, in _handle_dbapi_exception\n    raise exc_info[1].with_traceback(exc_info[2])\n  File \"/usr/local/lib/python3.12/site-packages/sqlalchemy/engine/base.py\", line 1145, in _commit_impl\n    self.engine.dialect.do_commit(self.connection)\n                                  ^^^^^^^^^^^^^^^\n  File \"/usr/local/lib/python3.12/site-packages/sqlalchemy/engine/base.py\", line 581, in connection\n    return self._revalidate_connection()\n           ^^^^^^^^^^^^^^^^^^^^^^^^^^^^^\n  File \"/usr/local/lib/python3.12/site-packages/sqlalchemy/engine/base.py\", line 673, in _revalidate_connection\n    self._invalid_transaction()\n  File \"/usr/local/lib/python3.12/site-packages/sqlalchemy/engine/base.py\", line 663, in _invalid_transaction\n    raise exc.PendingRollbackError(\nsqlalchemy.exc.PendingRollbackError: Can't reconnect until invalid transaction is rolled back.  Please rollback() fully before proceeding (Background on this error at: https://sqlalche.me/e/20/8s2b)",
    "insertId": "69fce6b3000bfe72ede827bf",
    "resource": {
      "type": "cloud_run_revision",
      "labels": {
        "location": "us-central1",
        "service_name": "scalpyn",
        "project_id": "clickrate-477217",
        "revision_name": "scalpyn-00443-w7q",
        "configuration_name": "scalpyn"
      }
    },
    "timestamp": "2026-05-07T19:23:31.786034Z",
    "severity": "ERROR",
    "labels": {
      "commit-sha": "f8c801f7afc98c5489a805be516f9814ad7963bc",
      "gcb-trigger-id": "806f4336-706a-404f-82be-dd0d5c01ebfa",
      "gcb-build-id": "262efc38-54bb-4063-9b69-4ad1e03943b1",
      "managed-by": "gcp-cloud-build-deploy-cloud-run",
      "instanceId": "0007b734d9a62281d226db90aee11253f4c315f280c79275243d7397d7a72c25d2df44286354750d38ca5d7a4646bb2cb2d633f3611c60772c6af764b9b75ff4e69e0f892501e10848cc24122ed74c",
      "gcb-trigger-region": "global"
    },
    "logName": "projects/clickrate-477217/logs/run.googleapis.com%2Fstderr",
    "receiveTimestamp": "2026-05-07T19:23:31.874477023Z",
    "errorGroups": [
      {
        "id": "COOzos3MktetkQE"
      }
    ]
  },
  {
    "textPayload": "Traceback (most recent call last):\n  File \"/usr/local/lib/python3.12/site-packages/sqlalchemy/pool/base.py\", line 373, in _close_connection\n    self._dialect.do_terminate(connection)\n  File \"/usr/local/lib/python3.12/site-packages/sqlalchemy/dialects/postgresql/asyncpg.py\", line 1127, in do_terminate\n    dbapi_connection.terminate()\n  File \"/usr/local/lib/python3.12/site-packages/sqlalchemy/connectors/asyncio.py\", line 402, in terminate\n    self.await_(asyncio.shield(self._terminate_graceful_close()))  # type: ignore[attr-defined] # noqa: E501\n    ^^^^^^^^^^^^^^^^^^^^^^^^^^^^^^^^^^^^^^^^^^^^^^^^^^^^^^^^^^^^^\n  File \"/usr/local/lib/python3.12/site-packages/sqlalchemy/util/_concurrency_py3k.py\", line 132, in await_only\n    return current.parent.switch(awaitable)  # type: ignore[no-any-return,attr-defined] # noqa: E501\n           ^^^^^^^^^^^^^^^^^^^^^^^^^^^^^^^^\n  File \"/usr/local/lib/python3.12/site-packages/sqlalchemy/util/_concurrency_py3k.py\", line 196, in greenlet_spawn\n    value = await result\n            ^^^^^^^^^^^^\n  File \"/usr/local/lib/python3.12/site-packages/sqlalchemy/dialects/postgresql/asyncpg.py\", line 912, in _terminate_graceful_close\n    await self._connection.close(timeout=2)\n  File \"/usr/local/lib/python3.12/site-packages/asyncpg/connection.py\", line 1513, in close\n    await self._protocol.close(timeout)\n  File \"asyncpg/protocol/protocol.pyx\", line 617, in close\n  File \"asyncpg/protocol/protocol.pyx\", line 650, in asyncpg.protocol.protocol.BaseProtocol._request_cancel\n  File \"/usr/local/lib/python3.12/site-packages/asyncpg/connection.py\", line 1682, in _cancel_current_command\n    self._cancellations.add(self._loop.create_task(self._cancel(waiter)))\n                            ^^^^^^^^^^^^^^^^^^^^^^^^^^^^^^^^^^^^^^^^^^^^\n  File \"/usr/local/lib/python3.12/asyncio/base_events.py\", line 455, in create_task\n    self._check_closed()\n  File \"/usr/local/lib/python3.12/asyncio/base_events.py\", line 545, in _check_closed\n    raise RuntimeError('Event loop is closed')\nRuntimeError: Event loop is closed",
    "insertId": "69fce6bf0005b30ee36a32d6",
    "resource": {
      "type": "cloud_run_revision",
      "labels": {
        "service_name": "scalpyn-worker-structural",
        "location": "us-central1",
        "project_id": "clickrate-477217",
        "configuration_name": "scalpyn-worker-structural",
        "revision_name": "scalpyn-worker-structural-00001-pjm"
      }
    },
    "timestamp": "2026-05-07T19:23:43.373518Z",
    "severity": "ERROR",
    "labels": {
      "commit-sha": "2800521f9db260bdc42c47fcafb01226b950df4a",
      "gcb-trigger-id": "806f4336-706a-404f-82be-dd0d5c01ebfa",
      "gcb-build-id": "7e0bb172-2c6d-416d-b487-ea69b3b95288",
      "instanceId": "0007b734d961918f522ec6cf9d115997454f94c724710282cc5822fffb6868a618f074c98e5382892d5d361910051e510637f1b5670202472a7a90bc3de1407d2d9bdae072958b29a94d8ed2278e11",
      "managed-by": "gcp-cloud-build-deploy-cloud-run",
      "gcb-trigger-region": "global"
    },
    "logName": "projects/clickrate-477217/logs/run.googleapis.com%2Fstderr",
    "receiveTimestamp": "2026-05-07T19:23:43.471620081Z",
    "errorGroups": [
      {
        "id": "CIaUi4fY3-nCJw"
      }
    ]
  },
  {
    "textPayload": "Container called exit(0).",
    "insertId": "69fce6c6000c1251074b34cd",
    "resource": {
      "type": "cloud_run_revision",
      "labels": {
        "location": "us-central1",
        "service_name": "scalpyn-beat",
        "revision_name": "scalpyn-beat-00001-lz4",
        "configuration_name": "scalpyn-beat",
        "project_id": "clickrate-477217"
      }
    },
    "timestamp": "2026-05-07T19:23:50.790954Z",
    "severity": "WARNING",
    "labels": {
      "instanceId": "0007b734d94b9b8c2b9aed75cdd101c53539b0789c39cac1cb9cf59aff33dfa604f4ad4c9da25db37b9ffb8c1ea3ab9376160d060f5f955ed893545d2b5450f0d6d189931b87f69046f08deeccab",
      "managed-by": "gcp-cloud-build-deploy-cloud-run",
      "gcb-trigger-region": "global",
      "gcb-trigger-id": "806f4336-706a-404f-82be-dd0d5c01ebfa",
      "commit-sha": "2800521f9db260bdc42c47fcafb01226b950df4a",
      "container_name": "placeholder-1",
      "gcb-build-id": "7e0bb172-2c6d-416d-b487-ea69b3b95288"
    },
    "logName": "projects/clickrate-477217/logs/run.googleapis.com%2Fvarlog%2Fsystem",
    "receiveTimestamp": "2026-05-07T19:23:50.796817069Z"
  },
  {
    "textPayload": "Container called exit(0).",
    "insertId": "69fce6d8000b38fde40df209",
    "resource": {
      "type": "cloud_run_revision",
      "labels": {
        "location": "us-central1",
        "service_name": "scalpyn",
        "revision_name": "scalpyn-00443-w7q",
        "configuration_name": "scalpyn",
        "project_id": "clickrate-477217"
      }
    },
    "timestamp": "2026-05-07T19:24:08.730628Z",
    "severity": "WARNING",
    "labels": {
      "commit-sha": "f8c801f7afc98c5489a805be516f9814ad7963bc",
      "gcb-trigger-id": "806f4336-706a-404f-82be-dd0d5c01ebfa",
      "gcb-build-id": "262efc38-54bb-4063-9b69-4ad1e03943b1",
      "container_name": "placeholder-1",
      "managed-by": "gcp-cloud-build-deploy-cloud-run",
      "instanceId": "0007b734d9a62281d226db90aee11253f4c315f280c79275243d7397d7a72c25d2df44286354750d38ca5d7a4646bb2cb2d633f3611c60772c6af764b9b75ff4e69e0f892501e10848cc24122ed74c",
      "gcb-trigger-region": "global"
    },
    "logName": "projects/clickrate-477217/logs/run.googleapis.com%2Fvarlog%2Fsystem",
    "receiveTimestamp": "2026-05-07T19:24:08.743969413Z"
  },
  {
    "textPayload": "The request failed because either the HTTP response was malformed or connection to the instance had an error. Additional troubleshooting documentation can be found at: https://cloud.google.com/run/docs/troubleshooting#malformed-response-or-connection-error",
    "insertId": "69fce6d90001c952ebd6df63",
    "httpRequest": {
      "requestMethod": "POST",
      "requestUrl": "https://scalpyn-wm56dfqgta-uc.a.run.app/api/auth/login",
      "requestSize": "516",
      "status": 503,
      "responseSize": "68",
      "userAgent": "Deno/2.1.4 (variant; SupabaseEdgeRuntime/1.74.0)",
      "remoteIp": "2a05:d018:1a8b:400a:9ae:8dd5:2c06:94ce",
      "serverIp": "2600:1901:81d5:200::",
      "latency": "0.001640225s",
      "protocol": "HTTP/1.1"
    },
    "resource": {
      "type": "cloud_run_revision",
      "labels": {
        "revision_name": "scalpyn-00443-w7q",
        "configuration_name": "scalpyn",
        "project_id": "clickrate-477217",
        "location": "us-central1",
        "service_name": "scalpyn"
      }
    },
    "timestamp": "2026-05-07T19:24:09.112126Z",
    "severity": "ERROR",
    "labels": {
      "commit-sha": "f8c801f7afc98c5489a805be516f9814ad7963bc",
      "gcb-trigger-id": "806f4336-706a-404f-82be-dd0d5c01ebfa",
      "gcb-build-id": "262efc38-54bb-4063-9b69-4ad1e03943b1",
      "managed-by": "gcp-cloud-build-deploy-cloud-run",
      "instanceId": "0007b734d9a62281d226db90aee11253f4c315f280c79275243d7397d7a72c25d2df44286354750d38ca5d7a4646bb2cb2d633f3611c60772c6af764b9b75ff4e69e0f892501e10848cc24122ed74c",
      "gcb-trigger-region": "global"
    },
    "logName": "projects/clickrate-477217/logs/run.googleapis.com%2Frequests",
    "trace": "projects/clickrate-477217/traces/648adf4a4cb35df448f9f8627cdc01d3",
    "receiveTimestamp": "2026-05-07T19:24:09.125169098Z",
    "spanId": "4f919fc3c03f2974",
    "traceSampled": true
  }
]