{"nodes": [{"id": "c_users_ricar_default_directory_arquivos_documentos_scalpyn_scalpyn_scalpyn_backend_app_api_ai_skills_py", "label": "ai_skills.py", "file_type": "code", "source_file": "C:\\Users\\ricar\\Default Directory\\ARQUIVOS - Documentos\\SCALPYN\\scalpyn\\scalpyn\\backend\\app\\api\\ai_skills.py", "source_location": "L1"}, {"id": "api_ai_skills_get_current_user_id", "label": "get_current_user_id()", "file_type": "code", "source_file": "C:\\Users\\ricar\\Default Directory\\ARQUIVOS - Documentos\\SCALPYN\\scalpyn\\scalpyn\\backend\\app\\api\\ai_skills.py", "source_location": "L33"}, {"id": "api_ai_skills_createskillrequest", "label": "CreateSkillRequest", "file_type": "code", "source_file": "C:\\Users\\ricar\\Default Directory\\ARQUIVOS - Documentos\\SCALPYN\\scalpyn\\scalpyn\\backend\\app\\api\\ai_skills.py", "source_location": "L53"}, {"id": "basemodel", "label": "BaseModel", "file_type": "code", "source_file": "", "source_location": ""}, {"id": "api_ai_skills_updateskillrequest", "label": "UpdateSkillRequest", "file_type": "code", "source_file": "C:\\Users\\ricar\\Default Directory\\ARQUIVOS - Documentos\\SCALPYN\\scalpyn\\scalpyn\\backend\\app\\api\\ai_skills.py", "source_location": "L61"}, {"id": "api_ai_skills_skill_to_dict", "label": "_skill_to_dict()", "file_type": "code", "source_file": "C:\\Users\\ricar\\Default Directory\\ARQUIVOS - Documentos\\SCALPYN\\scalpyn\\scalpyn\\backend\\app\\api\\ai_skills.py", "source_location": "L69"}, {"id": "api_ai_skills_get_defaults", "label": "get_defaults()", "file_type": "code", "source_file": "C:\\Users\\ricar\\Default Directory\\ARQUIVOS - Documentos\\SCALPYN\\scalpyn\\scalpyn\\backend\\app\\api\\ai_skills.py", "source_location": "L84"}, {"id": "api_ai_skills_list_skills", "label": "list_skills()", "file_type": "code", "source_file": "C:\\Users\\ricar\\Default Directory\\ARQUIVOS - Documentos\\SCALPYN\\scalpyn\\scalpyn\\backend\\app\\api\\ai_skills.py", "source_location": "L99"}, {"id": "api_ai_skills_create_skill", "label": "create_skill()", "file_type": "code", "source_file": "C:\\Users\\ricar\\Default Directory\\ARQUIVOS - Documentos\\SCALPYN\\scalpyn\\scalpyn\\backend\\app\\api\\ai_skills.py", "source_location": "L113"}, {"id": "api_ai_skills_update_skill", "label": "update_skill()", "file_type": "code", "source_file": "C:\\Users\\ricar\\Default Directory\\ARQUIVOS - Documentos\\SCALPYN\\scalpyn\\scalpyn\\backend\\app\\api\\ai_skills.py", "source_location": "L147"}, {"id": "api_ai_skills_delete_skill", "label": "delete_skill()", "file_type": "code", "source_file": "C:\\Users\\ricar\\Default Directory\\ARQUIVOS - Documentos\\SCALPYN\\scalpyn\\scalpyn\\backend\\app\\api\\ai_skills.py", "source_location": "L195"}, {"id": "api_ai_skills_rationale_1", "label": "AI Skills API \u2014 /api/ai-skills CRUD para gerenciamento de prompts de sistema (S", "file_type": "rationale", "source_file": "C:\\Users\\ricar\\Default Directory\\ARQUIVOS - Documentos\\SCALPYN\\scalpyn\\scalpyn\\backend\\app\\api\\ai_skills.py", "source_location": "L1"}, {"id": "api_ai_skills_rationale_87", "label": "Retorna os prompts hardcoded do ROLE_PROMPTS como refer\u00eancia.", "file_type": "rationale", "source_file": "C:\\Users\\ricar\\Default Directory\\ARQUIVOS - Documentos\\SCALPYN\\scalpyn\\scalpyn\\backend\\app\\api\\ai_skills.py", "source_location": "L87"}], "edges": [{"source": "c_users_ricar_default_directory_arquivos_documentos_scalpyn_scalpyn_scalpyn_backend_app_api_ai_skills_py", "target": "fastapi", "relation": "imports_from", "context": "import", "confidence": "EXTRACTED", "source_file": "C:\\Users\\ricar\\Default Directory\\ARQUIVOS - Documentos\\SCALPYN\\scalpyn\\scalpyn\\backend\\app\\api\\ai_skills.py", "source_location": "L6", "weight": 1.0}, {"source": "c_users_ricar_default_directory_arquivos_documentos_scalpyn_scalpyn_scalpyn_backend_app_api_ai_skills_py", "target": "fastapi_security", "relation": "imports_from", "context": "import", "confidence": "EXTRACTED", "source_file": "C:\\Users\\ricar\\Default Directory\\ARQUIVOS - Documentos\\SCALPYN\\scalpyn\\scalpyn\\backend\\app\\api\\ai_skills.py", "source_location": "L7", "weight": 1.0}, {"source": "c_users_ricar_default_directory_arquivos_documentos_scalpyn_scalpyn_scalpyn_backend_app_api_ai_skills_py", "target": "sqlalchemy_ext_asyncio", "relation": "imports_from", "context": "import", "confidence": "EXTRACTED", "source_file": "C:\\Users\\ricar\\Default Directory\\ARQUIVOS - Documentos\\SCALPYN\\scalpyn\\scalpyn\\backend\\app\\api\\ai_skills.py", "source_location": "L8", "weight": 1.0}, {"source": "c_users_ricar_default_directory_arquivos_documentos_scalpyn_scalpyn_scalpyn_backend_app_api_ai_skills_py", "target": "sqlalchemy", "relation": "imports_from", "context": "import", "confidence": "EXTRACTED", "source_file": "C:\\Users\\ricar\\Default Directory\\ARQUIVOS - Documentos\\SCALPYN\\scalpyn\\scalpyn\\backend\\app\\api\\ai_skills.py", "source_location": "L9", "weight": 1.0}, {"source": "c_users_ricar_default_directory_arquivos_documentos_scalpyn_scalpyn_scalpyn_backend_app_api_ai_skills_py", "target": "pydantic", "relation": "imports_from", "context": "import", "confidence": "EXTRACTED", "source_file": "C:\\Users\\ricar\\Default Directory\\ARQUIVOS - Documentos\\SCALPYN\\scalpyn\\scalpyn\\backend\\app\\api\\ai_skills.py", "source_location": "L10", "weight": 1.0}, {"source": "c_users_ricar_default_directory_arquivos_documentos_scalpyn_scalpyn_scalpyn_backend_app_api_ai_skills_py", "target": "typing", "relation": "imports_from", "context": "import", "confidence": "EXTRACTED", "source_file": "C:\\Users\\ricar\\Default Directory\\ARQUIVOS - Documentos\\SCALPYN\\scalpyn\\scalpyn\\backend\\app\\api\\ai_skills.py", "source_location": "L11", "weight": 1.0}, {"source": "c_users_ricar_default_directory_arquivos_documentos_scalpyn_scalpyn_scalpyn_backend_app_api_ai_skills_py", "target": "uuid", "relation": "imports_from", "context": "import", "confidence": "EXTRACTED", "source_file": "C:\\Users\\ricar\\Default Directory\\ARQUIVOS - Documentos\\SCALPYN\\scalpyn\\scalpyn\\backend\\app\\api\\ai_skills.py", "source_location": "L12", "weight": 1.0}, {"source": "c_users_ricar_default_directory_arquivos_documentos_scalpyn_scalpyn_scalpyn_backend_app_api_ai_skills_py", "target": "uuid", "relation": "imports", "context": "import", "confidence": "EXTRACTED", "source_file": "C:\\Users\\ricar\\Default Directory\\ARQUIVOS - Documentos\\SCALPYN\\scalpyn\\scalpyn\\backend\\app\\api\\ai_skills.py", "source_location": "L13", "weight": 1.0}, {"source": "c_users_ricar_default_directory_arquivos_documentos_scalpyn_scalpyn_scalpyn_backend_app_api_ai_skills_py", "target": "datetime", "relation": "imports_from", "context": "import", "confidence": "EXTRACTED", "source_file": "C:\\Users\\ricar\\Default Directory\\ARQUIVOS - Documentos\\SCALPYN\\scalpyn\\scalpyn\\backend\\app\\api\\ai_skills.py", "source_location": "L14", "weight": 1.0}, {"source": "c_users_ricar_default_directory_arquivos_documentos_scalpyn_scalpyn_scalpyn_backend_app_api_ai_skills_py", "target": "jwt", "relation": "imports", "context": "import", "confidence": "EXTRACTED", "source_file": "C:\\Users\\ricar\\Default Directory\\ARQUIVOS - Documentos\\SCALPYN\\scalpyn\\scalpyn\\backend\\app\\api\\ai_skills.py", "source_location": "L16", "weight": 1.0}, {"source": "c_users_ricar_default_directory_arquivos_documentos_scalpyn_scalpyn_scalpyn_backend_app_api_ai_skills_py", "target": "c_users_ricar_default_directory_arquivos_documentos_scalpyn_scalpyn_scalpyn_backend_app_config_py", "relation": "imports_from", "context": "import", "confidence": "EXTRACTED", "source_file": "C:\\Users\\ricar\\Default Directory\\ARQUIVOS - Documentos\\SCALPYN\\scalpyn\\scalpyn\\backend\\app\\api\\ai_skills.py", "source_location": "L18", "weight": 1.0}, {"source": "c_users_ricar_default_directory_arquivos_documentos_scalpyn_scalpyn_scalpyn_backend_app_api_ai_skills_py", "target": "c_users_ricar_default_directory_arquivos_documentos_scalpyn_scalpyn_scalpyn_backend_app_database_py", "relation": "imports_from", "context": "import", "confidence": "EXTRACTED", "source_file": "C:\\Users\\ricar\\Default Directory\\ARQUIVOS - Documentos\\SCALPYN\\scalpyn\\scalpyn\\backend\\app\\api\\ai_skills.py", "source_location": "L19", "weight": 1.0}, {"source": "c_users_ricar_default_directory_arquivos_documentos_scalpyn_scalpyn_scalpyn_backend_app_api_ai_skills_py", "target": "c_users_ricar_default_directory_arquivos_documentos_scalpyn_scalpyn_scalpyn_backend_app_models_ai_skill_py", "relation": "imports_from", "context": "import", "confidence": "EXTRACTED", "source_file": "C:\\Users\\ricar\\Default Directory\\ARQUIVOS - Documentos\\SCALPYN\\scalpyn\\scalpyn\\backend\\app\\api\\ai_skills.py", "source_location": "L20", "weight": 1.0}, {"source": "c_users_ricar_default_directory_arquivos_documentos_scalpyn_scalpyn_scalpyn_backend_app_api_ai_skills_py", "target": "c_users_ricar_default_directory_arquivos_documentos_scalpyn_scalpyn_scalpyn_backend_app_services_preset_ia_service_py", "relation": "imports_from", "context": "import", "confidence": "EXTRACTED", "source_file": "C:\\Users\\ricar\\Default Directory\\ARQUIVOS - Documentos\\SCALPYN\\scalpyn\\scalpyn\\backend\\app\\api\\ai_skills.py", "source_location": "L21", "weight": 1.0}, {"source": "c_users_ricar_default_directory_arquivos_documentos_scalpyn_scalpyn_scalpyn_backend_app_api_ai_skills_py", "target": "api_ai_skills_get_current_user_id", "relation": "contains", "confidence": "EXTRACTED", "source_file": "C:\\Users\\ricar\\Default Directory\\ARQUIVOS - Documentos\\SCALPYN\\scalpyn\\scalpyn\\backend\\app\\api\\ai_skills.py", "source_location": "L33", "weight": 1.0}, {"source": "c_users_ricar_default_directory_arquivos_documentos_scalpyn_scalpyn_scalpyn_backend_app_api_ai_skills_py", "target": "api_ai_skills_createskillrequest", "relation": "contains", "confidence": "EXTRACTED", "source_file": "C:\\Users\\ricar\\Default Directory\\ARQUIVOS - Documentos\\SCALPYN\\scalpyn\\scalpyn\\backend\\app\\api\\ai_skills.py", "source_location": "L53", "weight": 1.0}, {"source": "api_ai_skills_createskillrequest", "target": "basemodel", "relation": "inherits", "confidence": "EXTRACTED", "source_file": "C:\\Users\\ricar\\Default Directory\\ARQUIVOS - Documentos\\SCALPYN\\scalpyn\\scalpyn\\backend\\app\\api\\ai_skills.py", "source_location": "L53", "weight": 1.0}, {"source": "c_users_ricar_default_directory_arquivos_documentos_scalpyn_scalpyn_scalpyn_backend_app_api_ai_skills_py", "target": "api_ai_skills_updateskillrequest", "relation": "contains", "confidence": "EXTRACTED", "source_file": "C:\\Users\\ricar\\Default Directory\\ARQUIVOS - Documentos\\SCALPYN\\scalpyn\\scalpyn\\backend\\app\\api\\ai_skills.py", "source_location": "L61", "weight": 1.0}, {"source": "api_ai_skills_updateskillrequest", "target": "basemodel", "relation": "inherits", "confidence": "EXTRACTED", "source_file": "C:\\Users\\ricar\\Default Directory\\ARQUIVOS - Documentos\\SCALPYN\\scalpyn\\scalpyn\\backend\\app\\api\\ai_skills.py", "source_location": "L61", "weight": 1.0}, {"source": "c_users_ricar_default_directory_arquivos_documentos_scalpyn_scalpyn_scalpyn_backend_app_api_ai_skills_py", "target": "api_ai_skills_skill_to_dict", "relation": "contains", "confidence": "EXTRACTED", "source_file": "C:\\Users\\ricar\\Default Directory\\ARQUIVOS - Documentos\\SCALPYN\\scalpyn\\scalpyn\\backend\\app\\api\\ai_skills.py", "source_location": "L69", "weight": 1.0}, {"source": "c_users_ricar_default_directory_arquivos_documentos_scalpyn_scalpyn_scalpyn_backend_app_api_ai_skills_py", "target": "api_ai_skills_get_defaults", "relation": "contains", "confidence": "EXTRACTED", "source_file": "C:\\Users\\ricar\\Default Directory\\ARQUIVOS - Documentos\\SCALPYN\\scalpyn\\scalpyn\\backend\\app\\api\\ai_skills.py", "source_location": "L84", "weight": 1.0}, {"source": "c_users_ricar_default_directory_arquivos_documentos_scalpyn_scalpyn_scalpyn_backend_app_api_ai_skills_py", "target": "api_ai_skills_list_skills", "relation": "contains", "confidence": "EXTRACTED", "source_file": "C:\\Users\\ricar\\Default Directory\\ARQUIVOS - Documentos\\SCALPYN\\scalpyn\\scalpyn\\backend\\app\\api\\ai_skills.py", "source_location": "L99", "weight": 1.0}, {"source": "c_users_ricar_default_directory_arquivos_documentos_scalpyn_scalpyn_scalpyn_backend_app_api_ai_skills_py", "target": "api_ai_skills_create_skill", "relation": "contains", "confidence": "EXTRACTED", "source_file": "C:\\Users\\ricar\\Default Directory\\ARQUIVOS - Documentos\\SCALPYN\\scalpyn\\scalpyn\\backend\\app\\api\\ai_skills.py", "source_location": "L113", "weight": 1.0}, {"source": "c_users_ricar_default_directory_arquivos_documentos_scalpyn_scalpyn_scalpyn_backend_app_api_ai_skills_py", "target": "api_ai_skills_update_skill", "relation": "contains", "confidence": "EXTRACTED", "source_file": "C:\\Users\\ricar\\Default Directory\\ARQUIVOS - Documentos\\SCALPYN\\scalpyn\\scalpyn\\backend\\app\\api\\ai_skills.py", "source_location": "L147", "weight": 1.0}, {"source": "c_users_ricar_default_directory_arquivos_documentos_scalpyn_scalpyn_scalpyn_backend_app_api_ai_skills_py", "target": "api_ai_skills_delete_skill", "relation": "contains", "confidence": "EXTRACTED", "source_file": "C:\\Users\\ricar\\Default Directory\\ARQUIVOS - Documentos\\SCALPYN\\scalpyn\\scalpyn\\backend\\app\\api\\ai_skills.py", "source_location": "L195", "weight": 1.0}, {"source": "api_ai_skills_list_skills", "target": "api_ai_skills_skill_to_dict", "relation": "calls", "context": "call", "confidence": "EXTRACTED", "source_file": "C:\\Users\\ricar\\Default Directory\\ARQUIVOS - Documentos\\SCALPYN\\scalpyn\\scalpyn\\backend\\app\\api\\ai_skills.py", "source_location": "L109", "weight": 1.0}, {"source": "api_ai_skills_create_skill", "target": "api_ai_skills_skill_to_dict", "relation": "calls", "context": "call", "confidence": "EXTRACTED", "source_file": "C:\\Users\\ricar\\Default Directory\\ARQUIVOS - Documentos\\SCALPYN\\scalpyn\\scalpyn\\backend\\app\\api\\ai_skills.py", "source_location": "L143", "weight": 1.0}, {"source": "api_ai_skills_update_skill", "target": "api_ai_skills_skill_to_dict", "relation": "calls", "context": "call", "confidence": "EXTRACTED", "source_file": "C:\\Users\\ricar\\Default Directory\\ARQUIVOS - Documentos\\SCALPYN\\scalpyn\\scalpyn\\backend\\app\\api\\ai_skills.py", "source_location": "L191", "weight": 1.0}, {"source": "api_ai_skills_rationale_1", "target": "c_users_ricar_default_directory_arquivos_documentos_scalpyn_scalpyn_scalpyn_backend_app_api_ai_skills_py", "relation": "rationale_for", "confidence": "EXTRACTED", "source_file": "C:\\Users\\ricar\\Default Directory\\ARQUIVOS - Documentos\\SCALPYN\\scalpyn\\scalpyn\\backend\\app\\api\\ai_skills.py", "source_location": "L1", "weight": 1.0}, {"source": "api_ai_skills_rationale_87", "target": "api_ai_skills_get_defaults", "relation": "rationale_for", "confidence": "EXTRACTED", "source_file": "C:\\Users\\ricar\\Default Directory\\ARQUIVOS - Documentos\\SCALPYN\\scalpyn\\scalpyn\\backend\\app\\api\\ai_skills.py", "source_location": "L87", "weight": 1.0}], "raw_calls": [{"caller_nid": "api_ai_skills_get_current_user_id", "callee": "decode", "is_member_call": true, "source_file": "C:\\Users\\ricar\\Default Directory\\ARQUIVOS - Documentos\\SCALPYN\\scalpyn\\scalpyn\\backend\\app\\api\\ai_skills.py", "source_location": "L38"}, {"caller_nid": "api_ai_skills_get_current_user_id", "callee": "get", "is_member_call": true, "source_file": "C:\\Users\\ricar\\Default Directory\\ARQUIVOS - Documentos\\SCALPYN\\scalpyn\\scalpyn\\backend\\app\\api\\ai_skills.py", "source_location": "L39"}, {"caller_nid": "api_ai_skills_get_current_user_id", "callee": "HTTPException", "is_member_call": false, "source_file": "C:\\Users\\ricar\\Default Directory\\ARQUIVOS - Documentos\\SCALPYN\\scalpyn\\scalpyn\\backend\\app\\api\\ai_skills.py", "source_location": "L40"}, {"caller_nid": "api_ai_skills_get_current_user_id", "callee": "UUID", "is_member_call": false, "source_file": "C:\\Users\\ricar\\Default Directory\\ARQUIVOS - Documentos\\SCALPYN\\scalpyn\\scalpyn\\backend\\app\\api\\ai_skills.py", "source_location": "L41"}, {"caller_nid": "api_ai_skills_get_current_user_id", "callee": "HTTPException", "is_member_call": false, "source_file": "C:\\Users\\ricar\\Default Directory\\ARQUIVOS - Documentos\\SCALPYN\\scalpyn\\scalpyn\\backend\\app\\api\\ai_skills.py", "source_location": "L43"}, {"caller_nid": "api_ai_skills_get_current_user_id", "callee": "HTTPException", "is_member_call": false, "source_file": "C:\\Users\\ricar\\Default Directory\\ARQUIVOS - Documentos\\SCALPYN\\scalpyn\\scalpyn\\backend\\app\\api\\ai_skills.py", "source_location": "L47"}, {"caller_nid": "api_ai_skills_skill_to_dict", "callee": "str", "is_member_call": false, "source_file": "C:\\Users\\ricar\\Default Directory\\ARQUIVOS - Documentos\\SCALPYN\\scalpyn\\scalpyn\\backend\\app\\api\\ai_skills.py", "source_location": "L71"}, {"caller_nid": "api_ai_skills_skill_to_dict", "callee": "get", "is_member_call": true, "source_file": "C:\\Users\\ricar\\Default Directory\\ARQUIVOS - Documentos\\SCALPYN\\scalpyn\\scalpyn\\backend\\app\\api\\ai_skills.py", "source_location": "L75"}, {"caller_nid": "api_ai_skills_skill_to_dict", "callee": "isoformat", "is_member_call": true, "source_file": "C:\\Users\\ricar\\Default Directory\\ARQUIVOS - Documentos\\SCALPYN\\scalpyn\\scalpyn\\backend\\app\\api\\ai_skills.py", "source_location": "L78"}, {"caller_nid": "api_ai_skills_skill_to_dict", "callee": "isoformat", "is_member_call": true, "source_file": "C:\\Users\\ricar\\Default Directory\\ARQUIVOS - Documentos\\SCALPYN\\scalpyn\\scalpyn\\backend\\app\\api\\ai_skills.py", "source_location": "L79"}, {"caller_nid": "api_ai_skills_get_defaults", "callee": "get", "is_member_call": true, "source_file": "C:\\Users\\ricar\\Default Directory\\ARQUIVOS - Documentos\\SCALPYN\\scalpyn\\scalpyn\\backend\\app\\api\\ai_skills.py", "source_location": "L91"}, {"caller_nid": "api_ai_skills_get_defaults", "callee": "items", "is_member_call": true, "source_file": "C:\\Users\\ricar\\Default Directory\\ARQUIVOS - Documentos\\SCALPYN\\scalpyn\\scalpyn\\backend\\app\\api\\ai_skills.py", "source_location": "L94"}, {"caller_nid": "api_ai_skills_list_skills", "callee": "execute", "is_member_call": true, "source_file": "C:\\Users\\ricar\\Default Directory\\ARQUIVOS - Documentos\\SCALPYN\\scalpyn\\scalpyn\\backend\\app\\api\\ai_skills.py", "source_location": "L103"}, {"caller_nid": "api_ai_skills_list_skills", "callee": "order_by", "is_member_call": true, "source_file": "C:\\Users\\ricar\\Default Directory\\ARQUIVOS - Documentos\\SCALPYN\\scalpyn\\scalpyn\\backend\\app\\api\\ai_skills.py", "source_location": "L104"}, {"caller_nid": "api_ai_skills_list_skills", "callee": "where", "is_member_call": true, "source_file": "C:\\Users\\ricar\\Default Directory\\ARQUIVOS - Documentos\\SCALPYN\\scalpyn\\scalpyn\\backend\\app\\api\\ai_skills.py", "source_location": "L104"}, {"caller_nid": "api_ai_skills_list_skills", "callee": "select", "is_member_call": false, "source_file": "C:\\Users\\ricar\\Default Directory\\ARQUIVOS - Documentos\\SCALPYN\\scalpyn\\scalpyn\\backend\\app\\api\\ai_skills.py", "source_location": "L104"}, {"caller_nid": "api_ai_skills_list_skills", "callee": "asc", "is_member_call": true, "source_file": "C:\\Users\\ricar\\Default Directory\\ARQUIVOS - Documentos\\SCALPYN\\scalpyn\\scalpyn\\backend\\app\\api\\ai_skills.py", "source_location": "L106"}, {"caller_nid": "api_ai_skills_list_skills", "callee": "all", "is_member_call": true, "source_file": "C:\\Users\\ricar\\Default Directory\\ARQUIVOS - Documentos\\SCALPYN\\scalpyn\\scalpyn\\backend\\app\\api\\ai_skills.py", "source_location": "L108"}, {"caller_nid": "api_ai_skills_list_skills", "callee": "scalars", "is_member_call": true, "source_file": "C:\\Users\\ricar\\Default Directory\\ARQUIVOS - Documentos\\SCALPYN\\scalpyn\\scalpyn\\backend\\app\\api\\ai_skills.py", "source_location": "L108"}, {"caller_nid": "api_ai_skills_create_skill", "callee": "execute", "is_member_call": true, "source_file": "C:\\Users\\ricar\\Default Directory\\ARQUIVOS - Documentos\\SCALPYN\\scalpyn\\scalpyn\\backend\\app\\api\\ai_skills.py", "source_location": "L118"}, {"caller_nid": "api_ai_skills_create_skill", "callee": "where", "is_member_call": true, "source_file": "C:\\Users\\ricar\\Default Directory\\ARQUIVOS - Documentos\\SCALPYN\\scalpyn\\scalpyn\\backend\\app\\api\\ai_skills.py", "source_location": "L119"}, {"caller_nid": "api_ai_skills_create_skill", "callee": "select", "is_member_call": false, "source_file": "C:\\Users\\ricar\\Default Directory\\ARQUIVOS - Documentos\\SCALPYN\\scalpyn\\scalpyn\\backend\\app\\api\\ai_skills.py", "source_location": "L119"}, {"caller_nid": "api_ai_skills_create_skill", "callee": "and_", "is_member_call": false, "source_file": "C:\\Users\\ricar\\Default Directory\\ARQUIVOS - Documentos\\SCALPYN\\scalpyn\\scalpyn\\backend\\app\\api\\ai_skills.py", "source_location": "L120"}, {"caller_nid": "api_ai_skills_create_skill", "callee": "scalar_one_or_none", "is_member_call": true, "source_file": "C:\\Users\\ricar\\Default Directory\\ARQUIVOS - Documentos\\SCALPYN\\scalpyn\\scalpyn\\backend\\app\\api\\ai_skills.py", "source_location": "L123"}, {"caller_nid": "api_ai_skills_create_skill", "callee": "HTTPException", "is_member_call": false, "source_file": "C:\\Users\\ricar\\Default Directory\\ARQUIVOS - Documentos\\SCALPYN\\scalpyn\\scalpyn\\backend\\app\\api\\ai_skills.py", "source_location": "L124"}, {"caller_nid": "api_ai_skills_create_skill", "callee": "AiSkill", "is_member_call": false, "source_file": "C:\\Users\\ricar\\Default Directory\\ARQUIVOS - Documentos\\SCALPYN\\scalpyn\\scalpyn\\backend\\app\\api\\ai_skills.py", "source_location": "L129"}, {"caller_nid": "api_ai_skills_create_skill", "callee": "uuid4", "is_member_call": true, "source_file": "C:\\Users\\ricar\\Default Directory\\ARQUIVOS - Documentos\\SCALPYN\\scalpyn\\scalpyn\\backend\\app\\api\\ai_skills.py", "source_location": "L130"}, {"caller_nid": "api_ai_skills_create_skill", "callee": "now", "is_member_call": true, "source_file": "C:\\Users\\ricar\\Default Directory\\ARQUIVOS - Documentos\\SCALPYN\\scalpyn\\scalpyn\\backend\\app\\api\\ai_skills.py", "source_location": "L137"}, {"caller_nid": "api_ai_skills_create_skill", "callee": "now", "is_member_call": true, "source_file": "C:\\Users\\ricar\\Default Directory\\ARQUIVOS - Documentos\\SCALPYN\\scalpyn\\scalpyn\\backend\\app\\api\\ai_skills.py", "source_location": "L138"}, {"caller_nid": "api_ai_skills_create_skill", "callee": "add", "is_member_call": true, "source_file": "C:\\Users\\ricar\\Default Directory\\ARQUIVOS - Documentos\\SCALPYN\\scalpyn\\scalpyn\\backend\\app\\api\\ai_skills.py", "source_location": "L140"}, {"caller_nid": "api_ai_skills_create_skill", "callee": "commit", "is_member_call": true, "source_file": "C:\\Users\\ricar\\Default Directory\\ARQUIVOS - Documentos\\SCALPYN\\scalpyn\\scalpyn\\backend\\app\\api\\ai_skills.py", "source_location": "L141"}, {"caller_nid": "api_ai_skills_create_skill", "callee": "refresh", "is_member_call": true, "source_file": "C:\\Users\\ricar\\Default Directory\\ARQUIVOS - Documentos\\SCALPYN\\scalpyn\\scalpyn\\backend\\app\\api\\ai_skills.py", "source_location": "L142"}, {"caller_nid": "api_ai_skills_update_skill", "callee": "execute", "is_member_call": true, "source_file": "C:\\Users\\ricar\\Default Directory\\ARQUIVOS - Documentos\\SCALPYN\\scalpyn\\scalpyn\\backend\\app\\api\\ai_skills.py", "source_location": "L153"}, {"caller_nid": "api_ai_skills_update_skill", "callee": "where", "is_member_call": true, "source_file": "C:\\Users\\ricar\\Default Directory\\ARQUIVOS - Documentos\\SCALPYN\\scalpyn\\scalpyn\\backend\\app\\api\\ai_skills.py", "source_location": "L154"}, {"caller_nid": "api_ai_skills_update_skill", "callee": "select", "is_member_call": false, "source_file": "C:\\Users\\ricar\\Default Directory\\ARQUIVOS - Documentos\\SCALPYN\\scalpyn\\scalpyn\\backend\\app\\api\\ai_skills.py", "source_location": "L154"}, {"caller_nid": "api_ai_skills_update_skill", "callee": "and_", "is_member_call": false, "source_file": "C:\\Users\\ricar\\Default Directory\\ARQUIVOS - Documentos\\SCALPYN\\scalpyn\\scalpyn\\backend\\app\\api\\ai_skills.py", "source_location": "L155"}, {"caller_nid": "api_ai_skills_update_skill", "callee": "scalar_one_or_none", "is_member_call": true, "source_file": "C:\\Users\\ricar\\Default Directory\\ARQUIVOS - Documentos\\SCALPYN\\scalpyn\\scalpyn\\backend\\app\\api\\ai_skills.py", "source_location": "L158"}, {"caller_nid": "api_ai_skills_update_skill", "callee": "HTTPException", "is_member_call": false, "source_file": "C:\\Users\\ricar\\Default Directory\\ARQUIVOS - Documentos\\SCALPYN\\scalpyn\\scalpyn\\backend\\app\\api\\ai_skills.py", "source_location": "L160"}, {"caller_nid": "api_ai_skills_update_skill", "callee": "execute", "is_member_call": true, "source_file": "C:\\Users\\ricar\\Default Directory\\ARQUIVOS - Documentos\\SCALPYN\\scalpyn\\scalpyn\\backend\\app\\api\\ai_skills.py", "source_location": "L163"}, {"caller_nid": "api_ai_skills_update_skill", "callee": "where", "is_member_call": true, "source_file": "C:\\Users\\ricar\\Default Directory\\ARQUIVOS - Documentos\\SCALPYN\\scalpyn\\scalpyn\\backend\\app\\api\\ai_skills.py", "source_location": "L164"}, {"caller_nid": "api_ai_skills_update_skill", "callee": "select", "is_member_call": false, "source_file": "C:\\Users\\ricar\\Default Directory\\ARQUIVOS - Documentos\\SCALPYN\\scalpyn\\scalpyn\\backend\\app\\api\\ai_skills.py", "source_location": "L164"}, {"caller_nid": "api_ai_skills_update_skill", "callee": "and_", "is_member_call": false, "source_file": "C:\\Users\\ricar\\Default Directory\\ARQUIVOS - Documentos\\SCALPYN\\scalpyn\\scalpyn\\backend\\app\\api\\ai_skills.py", "source_location": "L165"}, {"caller_nid": "api_ai_skills_update_skill", "callee": "scalar_one_or_none", "is_member_call": true, "source_file": "C:\\Users\\ricar\\Default Directory\\ARQUIVOS - Documentos\\SCALPYN\\scalpyn\\scalpyn\\backend\\app\\api\\ai_skills.py", "source_location": "L172"}, {"caller_nid": "api_ai_skills_update_skill", "callee": "HTTPException", "is_member_call": false, "source_file": "C:\\Users\\ricar\\Default Directory\\ARQUIVOS - Documentos\\SCALPYN\\scalpyn\\scalpyn\\backend\\app\\api\\ai_skills.py", "source_location": "L173"}, {"caller_nid": "api_ai_skills_update_skill", "callee": "now", "is_member_call": true, "source_file": "C:\\Users\\ricar\\Default Directory\\ARQUIVOS - Documentos\\SCALPYN\\scalpyn\\scalpyn\\backend\\app\\api\\ai_skills.py", "source_location": "L188"}, {"caller_nid": "api_ai_skills_update_skill", "callee": "commit", "is_member_call": true, "source_file": "C:\\Users\\ricar\\Default Directory\\ARQUIVOS - Documentos\\SCALPYN\\scalpyn\\scalpyn\\backend\\app\\api\\ai_skills.py", "source_location": "L189"}, {"caller_nid": "api_ai_skills_update_skill", "callee": "refresh", "is_member_call": true, "source_file": "C:\\Users\\ricar\\Default Directory\\ARQUIVOS - Documentos\\SCALPYN\\scalpyn\\scalpyn\\backend\\app\\api\\ai_skills.py", "source_location": "L190"}, {"caller_nid": "api_ai_skills_delete_skill", "callee": "execute", "is_member_call": true, "source_file": "C:\\Users\\ricar\\Default Directory\\ARQUIVOS - Documentos\\SCALPYN\\scalpyn\\scalpyn\\backend\\app\\api\\ai_skills.py", "source_location": "L200"}, {"caller_nid": "api_ai_skills_delete_skill", "callee": "where", "is_member_call": true, "source_file": "C:\\Users\\ricar\\Default Directory\\ARQUIVOS - Documentos\\SCALPYN\\scalpyn\\scalpyn\\backend\\app\\api\\ai_skills.py", "source_location": "L201"}, {"caller_nid": "api_ai_skills_delete_skill", "callee": "select", "is_member_call": false, "source_file": "C:\\Users\\ricar\\Default Directory\\ARQUIVOS - Documentos\\SCALPYN\\scalpyn\\scalpyn\\backend\\app\\api\\ai_skills.py", "source_location": "L201"}, {"caller_nid": "api_ai_skills_delete_skill", "callee": "and_", "is_member_call": false, "source_file": "C:\\Users\\ricar\\Default Directory\\ARQUIVOS - Documentos\\SCALPYN\\scalpyn\\scalpyn\\backend\\app\\api\\ai_skills.py", "source_location": "L202"}, {"caller_nid": "api_ai_skills_delete_skill", "callee": "scalar_one_or_none", "is_member_call": true, "source_file": "C:\\Users\\ricar\\Default Directory\\ARQUIVOS - Documentos\\SCALPYN\\scalpyn\\scalpyn\\backend\\app\\api\\ai_skills.py", "source_location": "L205"}, {"caller_nid": "api_ai_skills_delete_skill", "callee": "HTTPException", "is_member_call": false, "source_file": "C:\\Users\\ricar\\Default Directory\\ARQUIVOS - Documentos\\SCALPYN\\scalpyn\\scalpyn\\backend\\app\\api\\ai_skills.py", "source_location": "L207"}, {"caller_nid": "api_ai_skills_delete_skill", "callee": "delete", "is_member_call": true, "source_file": "C:\\Users\\ricar\\Default Directory\\ARQUIVOS - Documentos\\SCALPYN\\scalpyn\\scalpyn\\backend\\app\\api\\ai_skills.py", "source_location": "L209"}, {"caller_nid": "api_ai_skills_delete_skill", "callee": "commit", "is_member_call": true, "source_file": "C:\\Users\\ricar\\Default Directory\\ARQUIVOS - Documentos\\SCALPYN\\scalpyn\\scalpyn\\backend\\app\\api\\ai_skills.py", "source_location": "L210"}, {"caller_nid": "api_ai_skills_delete_skill", "callee": "str", "is_member_call": false, "source_file": "C:\\Users\\ricar\\Default Directory\\ARQUIVOS - Documentos\\SCALPYN\\scalpyn\\scalpyn\\backend\\app\\api\\ai_skills.py", "source_location": "L211"}]}